{
  "file_number": "97",
  "violated_articles": [
    {
      "law": "개인정보보호법",
      "id": "제29조"
    },
    {
      "law": "시행령",
      "id": "제48조의2제1항"
    },
    {
      "law": "기술적 보호조치 기준",
      "id": "제4조제5항"
    },
    {
      "law": "기술적 보호조치 기준",
      "id": "제4조제9항"
    },
    {
      "law": "기술적 보호조치 기준",
      "id": "제6조제2항"
    },
    {
      "law": "개인정보보호법",
      "id": "제21조제1항"
    },
    {
      "law": "개인정보보호법",
      "id": "제39조의4제1항"
    },
    {
      "law": "시행령",
      "id": "제48조의4제2항"
    }
  ],
  "case_id": "제2024-018-242호"
}
