{
  "DECREE_C1": {
    "applicability": false,
    "legal": true
  },
  "DECREE_A1": {
    "applicability": false,
    "legal": true
  },
  "DECREE_A2": {
    "applicability": false,
    "legal": true
  },
  "DECREE_A2_S1": {
    "applicability": false,
    "legal": true
  },
  "DECREE_A2_S1_2": {
    "applicability": false,
    "legal": true
  },
  "DECREE_A2_S2": {
    "applicability": false,
    "legal": true
  },
  "DECREE_A2_S3": {
    "applicability": false,
    "legal": true
  },
  "DECREE_A2_S4": {
    "applicability": false,
    "legal": true
  },
  "DECREE_A2_S5": {
    "applicability": false,
    "legal": true
  },
  "DECREE_A3": {
    "applicability": false,
    "legal": true
  },
  "DECREE_A3_P1": {
    "applicability": false,
    "legal": true
  },
  "DECREE_A3_P1_S1": {
    "applicability": false,
    "legal": true
  },
  "DECREE_A3_P1_S1_Ia": {
    "applicability": false,
    "legal": true
  },
  "DECREE_A3_P1_S1_Ib": {
    "applicability": false,
    "legal": true
  },
  "DECREE_A3_P1_S2": {
    "applicability": false,
    "legal": true
  },
  "DECREE_A3_P2": {
    "applicability": false,
    "legal": true
  },
  "DECREE_A3_P2_S1": {
    "applicability": false,
    "legal": true
  },
  "DECREE_A3_P2_S2": {
    "applicability": false,
    "legal": true
  },
  "DECREE_A3_P2_S3": {
    "applicability": false,
    "legal": true
  },
  "DECREE_C2": {
    "applicability": false,
    "legal": true
  },
  "DECREE_A4_2": {
    "applicability": false,
    "legal": true
  },
  "DECREE_A4_2_S1": {
    "applicability": false,
    "legal": true
  },
  "DECREE_A4_2_S2": {
    "applicability": false,
    "legal": true
  },
  "DECREE_A5": {
    "applicability": false,
    "legal": true
  },
  "DECREE_A5_P1": {
    "applicability": false,
    "legal": true
  },
  "DECREE_A5_P1_S1": {
    "applicability": false,
    "legal": true
  },
  "DECREE_A5_P1_S2": {
    "applicability": false,
    "legal": true
  },
  "DECREE_A5_P2": {
    "applicability": false,
    "legal": true
  },
  "DECREE_A5_P2_S1": {
    "applicability": false,
    "legal": true
  },
  "DECREE_A5_P2_S2": {
    "applicability": false,
    "legal": true
  },
  "DECREE_A5_P2_S3": {
    "applicability": false,
    "legal": true
  },
  "DECREE_A5_P2_S4": {
    "applicability": false,
    "legal": true
  },
  "DECREE_A5_P3": {
    "applicability": false,
    "legal": true
  },
  "DECREE_A5_2": {
    "applicability": false,
    "legal": true
  },
  "DECREE_A5_2_P1": {
    "applicability": false,
    "legal": true
  },
  "DECREE_A5_2_P2": {
    "applicability": false,
    "legal": true
  },
  "DECREE_A5_2_P2_S1": {
    "applicability": false,
    "legal": true
  },
  "DECREE_A5_2_P2_S2": {
    "applicability": false,
    "legal": true
  },
  "DECREE_A5_2_P2_S3": {
    "applicability": false,
    "legal": true
  },
  "DECREE_A5_2_P2_S4": {
    "applicability": false,
    "legal": true
  },
  "DECREE_A5_2_P2_S5": {
    "applicability": false,
    "legal": true
  },
  "DECREE_A5_2_P2_S6": {
    "applicability": false,
    "legal": true
  },
  "DECREE_A5_2_P3": {
    "applicability": false,
    "legal": true
  },
  "DECREE_A5_2_P4": {
    "applicability": false,
    "legal": true
  },
  "DECREE_A5_2_P5": {
    "applicability": false,
    "legal": true
  },
  "DECREE_A5_2_P6": {
    "applicability": false,
    "legal": true
  },
  "DECREE_A5_2_P7": {
    "applicability": false,
    "legal": true
  },
  "DECREE_A5_3": {
    "applicability": false,
    "legal": true
  },
  "DECREE_A5_3_P1": {
    "applicability": false,
    "legal": true
  },
  "DECREE_A5_3_P2": {
    "applicability": false,
    "legal": true
  },
  "DECREE_A5_3_P2_S1": {
    "applicability": false,
    "legal": true
  },
  "DECREE_A5_3_P2_S2": {
    "applicability": false,
    "legal": true
  },
  "DECREE_A5_3_P2_S3": {
    "applicability": false,
    "legal": true
  },
  "DECREE_A5_3_P2_S4": {
    "applicability": false,
    "legal": true
  },
  "DECREE_A5_3_P3": {
    "applicability": false,
    "legal": true
  },
  "DECREE_A6": {
    "applicability": false,
    "legal": true
  },
  "DECREE_A7": {
    "applicability": false,
    "legal": true
  },
  "DECREE_A9": {
    "applicability": false,
    "legal": true
  },
  "DECREE_A9_2": {
    "applicability": false,
    "legal": true
  },
  "DECREE_A9_2_P1": {
    "applicability": false,
    "legal": true
  },
  "DECREE_A9_2_P2": {
    "applicability": false,
    "legal": true
  },
  "DECREE_A9_3": {
    "applicability": false,
    "legal": true
  },
  "DECREE_A9_3_P1": {
    "applicability": false,
    "legal": true
  },
  "DECREE_A9_3_P1_S1": {
    "applicability": false,
    "legal": true
  },
  "DECREE_A9_3_P1_S2": {
    "applicability": false,
    "legal": true
  },
  "DECREE_A9_3_P1_S3": {
    "applicability": false,
    "legal": true
  },
  "DECREE_A9_3_P2": {
    "applicability": false,
    "legal": true
  },
  "DECREE_A9_3_P2_S1": {
    "applicability": false,
    "legal": true
  },
  "DECREE_A9_3_P2_S2": {
    "applicability": false,
    "legal": true
  },
  "DECREE_A9_3_P2_S3": {
    "applicability": false,
    "legal": true
  },
  "DECREE_A9_3_P2_S4": {
    "applicability": false,
    "legal": true
  },
  "DECREE_A9_3_P3": {
    "applicability": false,
    "legal": true
  },
  "DECREE_A9_3_P4": {
    "applicability": false,
    "legal": true
  },
  "DECREE_A9_3_P5": {
    "applicability": false,
    "legal": true
  },
  "DECREE_A9_3_P6": {
    "applicability": false,
    "legal": true
  },
  "DECREE_C3": {
    "applicability": false,
    "legal": true
  },
  "DECREE_A11": {
    "applicability": false,
    "legal": true
  },
  "DECREE_A11_P1": {
    "applicability": false,
    "legal": true
  },
  "DECREE_A11_P2": {
    "applicability": false,
    "legal": true
  },
  "DECREE_A11_P3": {
    "applicability": false,
    "legal": true
  },
  "DECREE_A12": {
    "applicability": false,
    "legal": true
  },
  "DECREE_A12_P1": {
    "applicability": false,
    "legal": true
  },
  "DECREE_A12_P2": {
    "applicability": false,
    "legal": true
  },
  "DECREE_A12_P3": {
    "applicability": false,
    "legal": true
  },
  "DECREE_A13": {
    "applicability": false,
    "legal": true
  },
  "DECREE_A13_P1": {
    "applicability": false,
    "legal": true
  },
  "DECREE_A13_P1_S1": {
    "applicability": false,
    "legal": true
  },
  "DECREE_A13_P1_S2": {
    "applicability": false,
    "legal": true
  },
  "DECREE_A13_P1_S3": {
    "applicability": false,
    "legal": true
  },
  "DECREE_A13_P1_S4": {
    "applicability": false,
    "legal": true
  },
  "DECREE_A13_P1_S5": {
    "applicability": false,
    "legal": true
  },
  "DECREE_A13_P2": {
    "applicability": false,
    "legal": true
  },
  "DECREE_A13_P3": {
    "applicability": false,
    "legal": true
  },
  "DECREE_A13_2": {
    "applicability": false,
    "legal": true
  },
  "DECREE_A13_2_P1": {
    "applicability": false,
    "legal": true
  },
  "DECREE_A13_2_P1_S1": {
    "applicability": false,
    "legal": true
  },
  "DECREE_A13_2_P1_S2": {
    "applicability": false,
    "legal": true
  },
  "DECREE_A13_2_P1_S3": {
    "applicability": false,
    "legal": true
  },
  "DECREE_A13_2_P2": {
    "applicability": false,
    "legal": true
  },
  "DECREE_A13_2_P2_S1": {
    "applicability": false,
    "legal": true
  },
  "DECREE_A13_2_P2_S2": {
    "applicability": false,
    "legal": true
  },
  "DECREE_A13_2_P2_S3": {
    "applicability": false,
    "legal": true
  },
  "DECREE_A13_2_P2_S4": {
    "applicability": false,
    "legal": true
  },
  "DECREE_A13_2_P2_S5": {
    "applicability": false,
    "legal": true
  },
  "DECREE_A13_2_P3": {
    "applicability": false,
    "legal": true
  },
  "DECREE_A13_2_P4": {
    "applicability": false,
    "legal": true
  },
  "DECREE_A13_2_P5": {
    "applicability": false,
    "legal": true
  },
  "DECREE_A13_2_P5_S1": {
    "applicability": false,
    "legal": true
  },
  "DECREE_A13_2_P5_S2": {
    "applicability": false,
    "legal": true
  },
  "DECREE_A13_2_P5_S3": {
    "applicability": false,
    "legal": true
  },
  "DECREE_A13_2_P6": {
    "applicability": false,
    "legal": true
  },
  "DECREE_A13_2_P7": {
    "applicability": false,
    "legal": true
  },
  "DECREE_A13_2_P8": {
    "applicability": false,
    "legal": true
  },
  "DECREE_A14": {
    "applicability": false,
    "legal": true
  },
  "DECREE_C4": {
    "applicability": false,
    "legal": true
  },
  "DECREE_A14_2": {
    "applicability": false,
    "legal": true
  },
  "DECREE_A14_2_P1": {
    "applicability": false,
    "legal": true
  },
  "DECREE_A14_2_P1_S1": {
    "applicability": false,
    "legal": true
  },
  "DECREE_A14_2_P1_S2": {
    "applicability": false,
    "legal": true
  },
  "DECREE_A14_2_P1_S3": {
    "applicability": false,
    "legal": true
  },
  "DECREE_A14_2_P1_S4": {
    "applicability": false,
    "legal": true
  },
  "DECREE_A14_2_P2": {
    "applicability": false,
    "legal": true
  },
  "DECREE_A15": {
    "applicability": false,
    "legal": true
  },
  "DECREE_A15_S1": {
    "applicability": false,
    "legal": true
  },
  "DECREE_A15_S2": {
    "applicability": false,
    "legal": true
  },
  "DECREE_A15_S3": {
    "applicability": false,
    "legal": true
  },
  "DECREE_A15_S4": {
    "applicability": false,
    "legal": true
  },
  "DECREE_A15_S5": {
    "applicability": false,
    "legal": true
  },
  "DECREE_A15_S6": {
    "applicability": false,
    "legal": true
  },
  "DECREE_A15_S7": {
    "applicability": false,
    "legal": true
  },
  "DECREE_A15_S8": {
    "applicability": false,
    "legal": true
  },
  "DECREE_A15_2": {
    "applicability": false,
    "legal": true
  },
  "DECREE_A15_2_P1": {
    "applicability": false,
    "legal": true
  },
  "DECREE_A15_2_P1_S1": {
    "applicability": false,
    "legal": true
  },
  "DECREE_A15_2_P1_S2": {
    "applicability": false,
    "legal": true
  },
  "DECREE_A15_2_P2": {
    "applicability": false,
    "legal": true
  },
  "DECREE_A15_2_P2_S1": {
    "applicability": false,
    "legal": true
  },
  "DECREE_A15_2_P2_S2": {
    "applicability": false,
    "legal": true
  },
  "DECREE_A15_2_P3": {
    "applicability": false,
    "legal": true
  },
  "DECREE_A15_2_P3_S1": {
    "applicability": false,
    "legal": true
  },
  "DECREE_A15_2_P3_S2": {
    "applicability": false,
    "legal": true
  },
  "DECREE_A15_2_P3_S3": {
    "applicability": false,
    "legal": true
  },
  "DECREE_A15_2_P4": {
    "applicability": false,
    "legal": true
  },
  "DECREE_A15_2_P4_S1": {
    "applicability": false,
    "legal": true
  },
  "DECREE_A15_2_P4_S2": {
    "applicability": false,
    "legal": true
  },
  "DECREE_A15_2_P4_S3": {
    "applicability": false,
    "legal": true
  },
  "DECREE_A15_3": {
    "applicability": false,
    "legal": true
  },
  "DECREE_A15_3_P1": {
    "applicability": false,
    "legal": true
  },
  "DECREE_A15_3_P1_S1": {
    "applicability": false,
    "legal": true
  },
  "DECREE_A15_3_P1_S2": {
    "applicability": false,
    "legal": true
  },
  "DECREE_A15_3_P2": {
    "applicability": false,
    "legal": true
  },
  "DECREE_A15_3_P2_S1": {
    "applicability": false,
    "legal": true
  },
  "DECREE_A15_3_P2_S2": {
    "applicability": false,
    "legal": true
  },
  "DECREE_A15_3_P2_S3": {
    "applicability": false,
    "legal": true
  },
  "DECREE_A15_3_P2_S4": {
    "applicability": false,
    "legal": true
  },
  "DECREE_A15_3_P2_S5": {
    "applicability": false,
    "legal": true
  },
  "DECREE_A15_3_P3": {
    "applicability": false,
    "legal": true
  },
  "DECREE_A15_3_P3_S1": {
    "applicability": false,
    "legal": true
  },
  "DECREE_A15_3_P3_S2": {
    "applicability": false,
    "legal": true
  },
  "DECREE_A15_3_P4": {
    "applicability": false,
    "legal": true
  },
  "DECREE_A15_3_P4_S1": {
    "applicability": false,
    "legal": true
  },
  "DECREE_A15_3_P4_S2": {
    "applicability": false,
    "legal": true
  },
  "DECREE_A16": {
    "applicability": false,
    "legal": false
  },
  "DECREE_A16_P1": {
    "applicability": false,
    "legal": false
  },
  "DECREE_A16_P1_S1": {
    "applicability": false,
    "legal": false
  },
  "DECREE_A16_P1_S2": {
    "applicability": false,
    "legal": false
  },
  "DECREE_A16_P2": {
    "applicability": false,
    "legal": false
  },
  "DECREE_A17": {
    "applicability": false,
    "legal": false
  },
  "DECREE_A17_P1": {
    "applicability": false,
    "legal": false
  },
  "DECREE_A17_P1_S1": {
    "applicability": false,
    "legal": false
  },
  "DECREE_A17_P1_S2": {
    "applicability": false,
    "legal": false
  },
  "DECREE_A17_P1_S3": {
    "applicability": false,
    "legal": false
  },
  "DECREE_A17_P1_S4": {
    "applicability": false,
    "legal": false
  },
  "DECREE_A17_P2": {
    "applicability": false,
    "legal": false
  },
  "DECREE_A17_P2_S1": {
    "applicability": false,
    "legal": false
  },
  "DECREE_A17_P2_S2": {
    "applicability": false,
    "legal": false
  },
  "DECREE_A17_P2_S3": {
    "applicability": false,
    "legal": false
  },
  "DECREE_A17_P2_S4": {
    "applicability": false,
    "legal": false
  },
  "DECREE_A17_P2_S5": {
    "applicability": false,
    "legal": false
  },
  "DECREE_A17_P2_S6": {
    "applicability": false,
    "legal": false
  },
  "DECREE_A17_P3": {
    "applicability": false,
    "legal": false
  },
  "DECREE_A17_P3_S1": {
    "applicability": false,
    "legal": false
  },
  "DECREE_A17_P3_S2": {
    "applicability": false,
    "legal": false
  },
  "DECREE_A17_P3_S2_Ia": {
    "applicability": false,
    "legal": false
  },
  "DECREE_A17_P3_S2_Ib": {
    "applicability": false,
    "legal": false
  },
  "DECREE_A17_P3_S3": {
    "applicability": false,
    "legal": true
  },
  "DECREE_A17_P3_S4": {
    "applicability": false,
    "legal": false
  },
  "DECREE_A17_P4": {
    "applicability": false,
    "legal": false
  },
  "DECREE_A17_P5": {
    "applicability": false,
    "legal": false
  },
  "DECREE_A17_P6": {
    "applicability": false,
    "legal": false
  },
  "DECREE_A17_2": {
    "applicability": false,
    "legal": true
  },
  "DECREE_A17_2_P1": {
    "applicability": false,
    "legal": true
  },
  "DECREE_A17_2_P1_S1": {
    "applicability": false,
    "legal": true
  },
  "DECREE_A17_2_P1_S2": {
    "applicability": false,
    "legal": true
  },
  "DECREE_A17_2_P1_S3": {
    "applicability": false,
    "legal": true
  },
  "DECREE_A17_2_P1_S4": {
    "applicability": false,
    "legal": true
  },
  "DECREE_A17_2_P1_S5": {
    "applicability": false,
    "legal": true
  },
  "DECREE_A17_2_P1_S6": {
    "applicability": false,
    "legal": true
  },
  "DECREE_A17_2_P1_S7": {
    "applicability": false,
    "legal": true
  },
  "DECREE_A17_2_P2": {
    "applicability": false,
    "legal": true
  },
  "DECREE_A17_2_P3": {
    "applicability": false,
    "legal": true
  },
  "DECREE_A18": {
    "applicability": false,
    "legal": true
  },
  "DECREE_A18_S1": {
    "applicability": false,
    "legal": true
  },
  "DECREE_A18_S2": {
    "applicability": false,
    "legal": true
  },
  "DECREE_A18_S3": {
    "applicability": false,
    "legal": true
  },
  "DECREE_A18_S4": {
    "applicability": false,
    "legal": true
  },
  "DECREE_A19": {
    "applicability": false,
    "legal": true
  },
  "DECREE_A19_S1": {
    "applicability": false,
    "legal": true
  },
  "DECREE_A19_S2": {
    "applicability": false,
    "legal": true
  },
  "DECREE_A19_S3": {
    "applicability": false,
    "legal": true
  },
  "DECREE_A19_S4": {
    "applicability": false,
    "legal": true
  },
  "DECREE_A21": {
    "applicability": false,
    "legal": false
  },
  "DECREE_A21_P1": {
    "applicability": false,
    "legal": false
  },
  "DECREE_A21_P2": {
    "applicability": false,
    "legal": false
  },
  "DECREE_A21_P2_S1": {
    "applicability": false,
    "legal": false
  },
  "DECREE_A21_P2_S2": {
    "applicability": false,
    "legal": false
  },
  "DECREE_A21_P2_S3": {
    "applicability": false,
    "legal": false
  },
  "DECREE_A21_P3": {
    "applicability": false,
    "legal": true
  },
  "DECREE_A21_P4": {
    "applicability": false,
    "legal": false
  },
  "DECREE_A21_P4_S1": {
    "applicability": false,
    "legal": false
  },
  "DECREE_A21_P4_S2": {
    "applicability": false,
    "legal": false
  },
  "DECREE_A21_P4_S3": {
    "applicability": false,
    "legal": false
  },
  "DECREE_A21_P5": {
    "applicability": false,
    "legal": true
  },
  "DECREE_A21_P6": {
    "applicability": false,
    "legal": false
  },
  "DECREE_A21_P6_S1": {
    "applicability": false,
    "legal": false
  },
  "DECREE_A21_P6_S2": {
    "applicability": false,
    "legal": false
  },
  "DECREE_A21_2": {
    "applicability": false,
    "legal": false
  },
  "DECREE_A21_2_P1": {
    "applicability": false,
    "legal": false
  },
  "DECREE_A21_2_P2": {
    "applicability": false,
    "legal": true
  },
  "DECREE_A21_2_P2_S1": {
    "applicability": false,
    "legal": false
  },
  "DECREE_A21_2_P2_S2": {
    "applicability": false,
    "legal": false
  },
  "DECREE_A21_2_P3": {
    "applicability": false,
    "legal": false
  },
  "DECREE_A22": {
    "applicability": false,
    "legal": false
  },
  "DECREE_A22_P1": {
    "applicability": false,
    "legal": false
  },
  "DECREE_A22_P1_S1": {
    "applicability": true,
    "legal": false
  },
  "DECREE_A22_P1_S2": {
    "applicability": true,
    "legal": false
  },
  "DECREE_A22_P2": {
    "applicability": false,
    "legal": false
  },
  "DECREE_A22_P2_S1": {
    "applicability": false,
    "legal": false
  },
  "DECREE_A22_P2_S2": {
    "applicability": false,
    "legal": false
  },
  "DECREE_A22_P3": {
    "applicability": false,
    "legal": false
  },
  "DECREE_A23": {
    "applicability": false,
    "legal": true
  },
  "DECREE_A23_P1": {
    "applicability": false,
    "legal": true
  },
  "DECREE_A23_P1_S1": {
    "applicability": false,
    "legal": true
  },
  "DECREE_A23_P1_S2": {
    "applicability": false,
    "legal": true
  },
  "DECREE_A23_P2": {
    "applicability": false,
    "legal": true
  },
  "DECREE_A23_P2_S1": {
    "applicability": false,
    "legal": true
  },
  "DECREE_A23_P2_S2": {
    "applicability": false,
    "legal": true
  },
  "DECREE_A24": {
    "applicability": false,
    "legal": true
  },
  "DECREE_A24_P1": {
    "applicability": false,
    "legal": true
  },
  "DECREE_A24_P1_S1": {
    "applicability": false,
    "legal": true
  },
  "DECREE_A24_P1_S2": {
    "applicability": false,
    "legal": true
  },
  "DECREE_A24_P1_S3": {
    "applicability": false,
    "legal": true
  },
  "DECREE_A24_P2": {
    "applicability": false,
    "legal": true
  },
  "DECREE_A24_P2_S1": {
    "applicability": false,
    "legal": true
  },
  "DECREE_A24_P2_S2": {
    "applicability": false,
    "legal": true
  },
  "DECREE_A24_P3": {
    "applicability": false,
    "legal": true
  },
  "DECREE_A24_P3_S1": {
    "applicability": false,
    "legal": true
  },
  "DECREE_A24_P3_S2": {
    "applicability": false,
    "legal": true
  },
  "DECREE_A24_P4": {
    "applicability": false,
    "legal": true
  },
  "DECREE_A25": {
    "applicability": false,
    "legal": true
  },
  "DECREE_A25_P1": {
    "applicability": false,
    "legal": true
  },
  "DECREE_A25_P1_S1": {
    "applicability": false,
    "legal": true
  },
  "DECREE_A25_P1_S2": {
    "applicability": false,
    "legal": true
  },
  "DECREE_A25_P1_S3": {
    "applicability": false,
    "legal": true
  },
  "DECREE_A25_P1_S4": {
    "applicability": false,
    "legal": true
  },
  "DECREE_A25_P1_S5": {
    "applicability": false,
    "legal": true
  },
  "DECREE_A25_P1_S6": {
    "applicability": false,
    "legal": true
  },
  "DECREE_A25_P1_S7": {
    "applicability": false,
    "legal": true
  },
  "DECREE_A25_P1_S8": {
    "applicability": false,
    "legal": true
  },
  "DECREE_A25_P2": {
    "applicability": false,
    "legal": true
  },
  "DECREE_A26": {
    "applicability": false,
    "legal": true
  },
  "DECREE_A26_P1": {
    "applicability": false,
    "legal": true
  },
  "DECREE_A26_P1_S1": {
    "applicability": false,
    "legal": true
  },
  "DECREE_A26_P1_S2": {
    "applicability": false,
    "legal": true
  },
  "DECREE_A26_P1_S3": {
    "applicability": false,
    "legal": true
  },
  "DECREE_A26_P1_S4": {
    "applicability": false,
    "legal": true
  },
  "DECREE_A26_P1_S5": {
    "applicability": false,
    "legal": true
  },
  "DECREE_A26_P2": {
    "applicability": false,
    "legal": true
  },
  "DECREE_A27": {
    "applicability": false,
    "legal": true
  },
  "DECREE_A27_2": {
    "applicability": false,
    "legal": true
  },
  "DECREE_A27_3": {
    "applicability": false,
    "legal": true
  },
  "DECREE_A28": {
    "applicability": true,
    "legal": false
  },
  "DECREE_A28_P1": {
    "applicability": true,
    "legal": false
  },
  "DECREE_A28_P1_S1": {
    "applicability": true,
    "legal": false
  },
  "DECREE_A28_P1_S2": {
    "applicability": true,
    "legal": false
  },
  "DECREE_A28_P1_S3": {
    "applicability": true,
    "legal": false
  },
  "DECREE_A28_P1_S4": {
    "applicability": true,
    "legal": false
  },
  "DECREE_A28_P1_S5": {
    "applicability": false,
    "legal": false
  },
  "DECREE_A28_P2": {
    "applicability": true,
    "legal": false
  },
  "DECREE_A28_P3": {
    "applicability": true,
    "legal": false
  },
  "DECREE_A28_P3_S1": {
    "applicability": true,
    "legal": false
  },
  "DECREE_A28_P3_S2": {
    "applicability": false,
    "legal": false
  },
  "DECREE_A28_P3_S3": {
    "applicability": true,
    "legal": false
  },
  "DECREE_A28_P3_S4": {
    "applicability": false,
    "legal": false
  },
  "DECREE_A28_P4": {
    "applicability": false,
    "legal": false
  },
  "DECREE_A28_P5": {
    "applicability": true,
    "legal": false
  },
  "DECREE_A28_P6": {
    "applicability": true,
    "legal": true
  },
  "DECREE_A29": {
    "applicability": true,
    "legal": false
  },
  "DECREE_A29_P1": {
    "applicability": false,
    "legal": false
  },
  "DECREE_A29_P2": {
    "applicability": false,
    "legal": true
  },
  "DECREE_A29_P2_S1": {
    "applicability": false,
    "legal": false
  },
  "DECREE_A29_P2_S2": {
    "applicability": false,
    "legal": true
  },
  "DECREE_A29_2": {
    "applicability": false,
    "legal": true
  },
  "DECREE_A29_2_P1": {
    "applicability": false,
    "legal": true
  },
  "DECREE_A29_2_P1_S1": {
    "applicability": false,
    "legal": true
  },
  "DECREE_A29_2_P1_S2": {
    "applicability": false,
    "legal": true
  },
  "DECREE_A29_2_P1_S3": {
    "applicability": false,
    "legal": true
  },
  "DECREE_A29_2_P1_S4": {
    "applicability": false,
    "legal": true
  },
  "DECREE_A29_2_P1_S5": {
    "applicability": false,
    "legal": true
  },
  "DECREE_A29_2_P2": {
    "applicability": false,
    "legal": true
  },
  "DECREE_A29_2_P2_S1": {
    "applicability": false,
    "legal": true
  },
  "DECREE_A29_2_P2_S2": {
    "applicability": false,
    "legal": true
  },
  "DECREE_A29_2_P3": {
    "applicability": false,
    "legal": true
  },
  "DECREE_A29_2_P4": {
    "applicability": false,
    "legal": true
  },
  "DECREE_A29_2_P4_S1": {
    "applicability": false,
    "legal": true
  },
  "DECREE_A29_2_P4_S2": {
    "applicability": false,
    "legal": true
  },
  "DECREE_A29_2_P4_S3": {
    "applicability": false,
    "legal": true
  },
  "DECREE_A29_2_P4_S4": {
    "applicability": false,
    "legal": true
  },
  "DECREE_A29_2_P5": {
    "applicability": false,
    "legal": true
  },
  "DECREE_A29_2_P5_S1": {
    "applicability": false,
    "legal": true
  },
  "DECREE_A29_2_P5_S2": {
    "applicability": false,
    "legal": true
  },
  "DECREE_A29_2_P5_S3": {
    "applicability": false,
    "legal": true
  },
  "DECREE_A29_2_P5_S4": {
    "applicability": false,
    "legal": true
  },
  "DECREE_A29_2_P5_S5": {
    "applicability": false,
    "legal": true
  },
  "DECREE_A29_2_P6": {
    "applicability": false,
    "legal": true
  },
  "DECREE_A29_2_P7": {
    "applicability": false,
    "legal": true
  },
  "DECREE_A29_2_P8": {
    "applicability": false,
    "legal": true
  },
  "DECREE_A29_3": {
    "applicability": false,
    "legal": true
  },
  "DECREE_A29_3_P1": {
    "applicability": false,
    "legal": true
  },
  "DECREE_A29_3_P1_S1": {
    "applicability": false,
    "legal": true
  },
  "DECREE_A29_3_P1_S2": {
    "applicability": false,
    "legal": true
  },
  "DECREE_A29_3_P1_S3": {
    "applicability": false,
    "legal": true
  },
  "DECREE_A29_3_P1_S4": {
    "applicability": false,
    "legal": true
  },
  "DECREE_A29_3_P2": {
    "applicability": false,
    "legal": true
  },
  "DECREE_A29_3_P3": {
    "applicability": false,
    "legal": true
  },
  "DECREE_A29_3_P4": {
    "applicability": false,
    "legal": true
  },
  "DECREE_A29_3_P4_S1": {
    "applicability": false,
    "legal": true
  },
  "DECREE_A29_3_P4_S2": {
    "applicability": false,
    "legal": true
  },
  "DECREE_A29_3_P4_S3": {
    "applicability": false,
    "legal": true
  },
  "DECREE_A29_3_P5": {
    "applicability": false,
    "legal": true
  },
  "DECREE_A29_3_P6": {
    "applicability": false,
    "legal": true
  },
  "DECREE_A29_4": {
    "applicability": false,
    "legal": true
  },
  "DECREE_A29_4_P1": {
    "applicability": false,
    "legal": true
  },
  "DECREE_A29_4_P2": {
    "applicability": false,
    "legal": true
  },
  "DECREE_A29_4_P2_S1": {
    "applicability": false,
    "legal": true
  },
  "DECREE_A29_4_P2_S2": {
    "applicability": false,
    "legal": true
  },
  "DECREE_A29_4_P2_S3": {
    "applicability": false,
    "legal": true
  },
  "DECREE_A29_4_P3": {
    "applicability": false,
    "legal": true
  },
  "DECREE_A29_4_P3_S1": {
    "applicability": false,
    "legal": true
  },
  "DECREE_A29_4_P3_S2": {
    "applicability": false,
    "legal": true
  },
  "DECREE_A29_4_P3_S3": {
    "applicability": false,
    "legal": true
  },
  "DECREE_A29_5": {
    "applicability": false,
    "legal": false
  },
  "DECREE_A29_5_P1": {
    "applicability": false,
    "legal": false
  },
  "DECREE_A29_5_P1_S1": {
    "applicability": false,
    "legal": true
  },
  "DECREE_A29_5_P1_S2": {
    "applicability": false,
    "legal": false
  },
  "DECREE_A29_5_P1_S3": {
    "applicability": false,
    "legal": false
  },
  "DECREE_A29_5_P2": {
    "applicability": false,
    "legal": true
  },
  "DECREE_A29_5_P2_S1": {
    "applicability": false,
    "legal": false
  },
  "DECREE_A29_5_P2_S2": {
    "applicability": false,
    "legal": false
  },
  "DECREE_A29_5_P2_S3": {
    "applicability": false,
    "legal": false
  },
  "DECREE_A29_5_P2_S4": {
    "applicability": false,
    "legal": false
  },
  "DECREE_A29_5_P2_S5": {
    "applicability": false,
    "legal": false
  },
  "DECREE_A29_5_P2_S6": {
    "applicability": false,
    "legal": false
  },
  "DECREE_A29_7": {
    "applicability": false,
    "legal": false
  },
  "DECREE_A29_8": {
    "applicability": false,
    "legal": true
  },
  "DECREE_A29_8_P1": {
    "applicability": false,
    "legal": true
  },
  "DECREE_A29_8_P1_S1": {
    "applicability": false,
    "legal": true
  },
  "DECREE_A29_8_P1_S2": {
    "applicability": false,
    "legal": true
  },
  "DECREE_A29_8_P1_S3": {
    "applicability": false,
    "legal": true
  },
  "DECREE_A29_8_P2": {
    "applicability": false,
    "legal": true
  },
  "DECREE_A29_8_P3": {
    "applicability": false,
    "legal": true
  },
  "DECREE_A29_9": {
    "applicability": false,
    "legal": true
  },
  "DECREE_A29_9_P1": {
    "applicability": false,
    "legal": true
  },
  "DECREE_A29_9_P1_S1": {
    "applicability": false,
    "legal": true
  },
  "DECREE_A29_9_P1_S2": {
    "applicability": false,
    "legal": true
  },
  "DECREE_A29_9_P1_S3": {
    "applicability": false,
    "legal": true
  },
  "DECREE_A29_9_P1_S4": {
    "applicability": false,
    "legal": true
  },
  "DECREE_A29_9_P1_S5": {
    "applicability": false,
    "legal": true
  },
  "DECREE_A29_9_P1_S6": {
    "applicability": false,
    "legal": true
  },
  "DECREE_A29_9_P2": {
    "applicability": false,
    "legal": true
  },
  "DECREE_A29_9_P2_S1": {
    "applicability": false,
    "legal": true
  },
  "DECREE_A29_9_P2_S2": {
    "applicability": false,
    "legal": true
  },
  "DECREE_A29_9_P3": {
    "applicability": false,
    "legal": true
  },
  "DECREE_A29_9_P4": {
    "applicability": false,
    "legal": true
  },
  "DECREE_A29_9_P5": {
    "applicability": false,
    "legal": true
  },
  "DECREE_A29_9_P6": {
    "applicability": false,
    "legal": true
  },
  "DECREE_A29_9_P7": {
    "applicability": false,
    "legal": true
  },
  "DECREE_A29_10": {
    "applicability": false,
    "legal": false
  },
  "DECREE_A29_10_P1": {
    "applicability": false,
    "legal": false
  },
  "DECREE_A29_10_P1_S1": {
    "applicability": false,
    "legal": false
  },
  "DECREE_A29_10_P1_S2": {
    "applicability": false,
    "legal": true
  },
  "DECREE_A29_10_P1_S3": {
    "applicability": false,
    "legal": true
  },
  "DECREE_A29_10_P2": {
    "applicability": false,
    "legal": false
  },
  "DECREE_A29_11": {
    "applicability": false,
    "legal": true
  },
  "DECREE_A29_11_P1": {
    "applicability": false,
    "legal": true
  },
  "DECREE_A29_11_P1_S1": {
    "applicability": false,
    "legal": true
  },
  "DECREE_A29_11_P1_S2": {
    "applicability": false,
    "legal": true
  },
  "DECREE_A29_11_P1_S3": {
    "applicability": false,
    "legal": true
  },
  "DECREE_A29_11_P1_S4": {
    "applicability": false,
    "legal": true
  },
  "DECREE_A29_11_P1_S5": {
    "applicability": false,
    "legal": true
  },
  "DECREE_A29_11_P1_S6": {
    "applicability": false,
    "legal": true
  },
  "DECREE_A29_11_P1_S7": {
    "applicability": false,
    "legal": true
  },
  "DECREE_A29_11_P2": {
    "applicability": false,
    "legal": true
  },
  "DECREE_A29_11_P3": {
    "applicability": false,
    "legal": true
  },
  "DECREE_A29_11_P4": {
    "applicability": false,
    "legal": true
  },
  "DECREE_A29_12": {
    "applicability": false,
    "legal": true
  },
  "DECREE_A29_12_P1": {
    "applicability": false,
    "legal": true
  },
  "DECREE_A29_12_P2": {
    "applicability": false,
    "legal": true
  },
  "DECREE_A29_12_P3": {
    "applicability": false,
    "legal": true
  },
  "DECREE_C5": {
    "applicability": false,
    "legal": true
  },
  "DECREE_A30": {
    "applicability": true,
    "legal": false
  },
  "DECREE_A30_P1": {
    "applicability": true,
    "legal": false
  },
  "DECREE_A30_P1_S1": {
    "applicability": true,
    "legal": false
  },
  "DECREE_A30_P1_S1_Ia": {
    "applicability": false,
    "legal": false
  },
  "DECREE_A30_P1_S1_Ib": {
    "applicability": false,
    "legal": false
  },
  "DECREE_A30_P1_S1_Ic": {
    "applicability": false,
    "legal": false
  },
  "DECREE_A30_P1_S2": {
    "applicability": true,
    "legal": true
  },
  "DECREE_A30_P1_S2_Ia": {
    "applicability": false,
    "legal": false
  },
  "DECREE_A30_P1_S2_Ib": {
    "applicability": false,
    "legal": false
  },
  "DECREE_A30_P1_S2_Ic": {
    "applicability": true,
    "legal": false
  },
  "DECREE_A30_P1_S3": {
    "applicability": false,
    "legal": false
  },
  "DECREE_A30_P1_S3_Ia": {
    "applicability": false,
    "legal": false
  },
  "DECREE_A30_P1_S3_Ib": {
    "applicability": false,
    "legal": false
  },
  "DECREE_A30_P1_S3_Ic": {
    "applicability": false,
    "legal": false
  },
  "DECREE_A30_P1_S4": {
    "applicability": false,
    "legal": false
  },
  "DECREE_A30_P1_S4_Ia": {
    "applicability": false,
    "legal": false
  },
  "DECREE_A30_P1_S4_Ib": {
    "applicability": false,
    "legal": false
  },
  "DECREE_A30_P1_S4_Ic": {
    "applicability": false,
    "legal": false
  },
  "DECREE_A30_P1_S4_Id": {
    "applicability": false,
    "legal": true
  },
  "DECREE_A30_P1_S5": {
    "applicability": false,
    "legal": false
  },
  "DECREE_A30_P1_S5_Ia": {
    "applicability": false,
    "legal": false
  },
  "DECREE_A30_P1_S5_Ib": {
    "applicability": false,
    "legal": false
  },
  "DECREE_A30_P1_S5_Ic": {
    "applicability": false,
    "legal": false
  },
  "DECREE_A30_P1_S6": {
    "applicability": false,
    "legal": false
  },
  "DECREE_A30_P1_S7": {
    "applicability": false,
    "legal": false
  },
  "DECREE_A30_P1_S8": {
    "applicability": true,
    "legal": true
  },
  "DECREE_A30_P2": {
    "applicability": true,
    "legal": false
  },
  "DECREE_A30_P3": {
    "applicability": true,
    "legal": false
  },
  "DECREE_A30_2": {
    "applicability": false,
    "legal": true
  },
  "DECREE_A30_2_P1": {
    "applicability": false,
    "legal": true
  },
  "DECREE_A30_2_P1_S1": {
    "applicability": false,
    "legal": true
  },
  "DECREE_A30_2_P1_S2": {
    "applicability": false,
    "legal": true
  },
  "DECREE_A30_2_P1_S3": {
    "applicability": false,
    "legal": true
  },
  "DECREE_A30_2_P2": {
    "applicability": false,
    "legal": true
  },
  "DECREE_A30_2_P2_S1": {
    "applicability": false,
    "legal": true
  },
  "DECREE_A30_2_P2_S2": {
    "applicability": false,
    "legal": true
  },
  "DECREE_A30_2_P3": {
    "applicability": false,
    "legal": true
  },
  "DECREE_A30_2_P4": {
    "applicability": false,
    "legal": true
  },
  "DECREE_A30_2_P5": {
    "applicability": false,
    "legal": true
  },
  "DECREE_A30_2_P5_S1": {
    "applicability": false,
    "legal": true
  },
  "DECREE_A30_2_P5_S2": {
    "applicability": false,
    "legal": true
  },
  "DECREE_A30_2_P5_S3": {
    "applicability": false,
    "legal": true
  },
  "DECREE_A30_2_P6": {
    "applicability": false,
    "legal": true
  },
  "DECREE_A30_2_P7": {
    "applicability": false,
    "legal": true
  },
  "DECREE_A31": {
    "applicability": true,
    "legal": false
  },
  "DECREE_A31_P1": {
    "applicability": false,
    "legal": false
  },
  "DECREE_A31_P1_S1": {
    "applicability": false,
    "legal": false
  },
  "DECREE_A31_P1_S2": {
    "applicability": false,
    "legal": true
  },
  "DECREE_A31_P1_S3": {
    "applicability": false,
    "legal": false
  },
  "DECREE_A31_P1_S4": {
    "applicability": false,
    "legal": false
  },
  "DECREE_A31_P2": {
    "applicability": false,
    "legal": false
  },
  "DECREE_A31_P3": {
    "applicability": true,
    "legal": true
  },
  "DECREE_A31_P3_S1": {
    "applicability": true,
    "legal": true
  },
  "DECREE_A31_P3_S2": {
    "applicability": false,
    "legal": false
  },
  "DECREE_A31_P3_S3": {
    "applicability": false,
    "legal": false
  },
  "DECREE_A31_P3_S4": {
    "applicability": true,
    "legal": true
  },
  "DECREE_A31_2": {
    "applicability": false,
    "legal": true
  },
  "DECREE_A31_2_P1": {
    "applicability": false,
    "legal": true
  },
  "DECREE_A31_2_P1_S1": {
    "applicability": false,
    "legal": true
  },
  "DECREE_A31_2_P1_S2": {
    "applicability": false,
    "legal": true
  },
  "DECREE_A31_2_P1_S3": {
    "applicability": false,
    "legal": true
  },
  "DECREE_A31_2_P1_S4": {
    "applicability": false,
    "legal": true
  },
  "DECREE_A31_2_P1_S5": {
    "applicability": false,
    "legal": true
  },
  "DECREE_A31_2_P2": {
    "applicability": false,
    "legal": true
  },
  "DECREE_A31_2_P3": {
    "applicability": false,
    "legal": true
  },
  "DECREE_A31_2_P4": {
    "applicability": false,
    "legal": true
  },
  "DECREE_A31_2_P5": {
    "applicability": false,
    "legal": true
  },
  "DECREE_A32": {
    "applicability": false,
    "legal": true
  },
  "DECREE_A32_P1": {
    "applicability": false,
    "legal": true
  },
  "DECREE_A32_P2": {
    "applicability": false,
    "legal": true
  },
  "DECREE_A32_P2_S1": {
    "applicability": false,
    "legal": true
  },
  "DECREE_A32_P2_S2": {
    "applicability": false,
    "legal": true
  },
  "DECREE_A32_P2_S3": {
    "applicability": false,
    "legal": true
  },
  "DECREE_A32_P3": {
    "applicability": false,
    "legal": true
  },
  "DECREE_A32_P3_S1": {
    "applicability": false,
    "legal": true
  },
  "DECREE_A32_P3_S1_Ia": {
    "applicability": false,
    "legal": true
  },
  "DECREE_A32_P3_S1_Ib": {
    "applicability": false,
    "legal": true
  },
  "DECREE_A32_P3_S1_Ic": {
    "applicability": false,
    "legal": true
  },
  "DECREE_A32_P3_S1_Id": {
    "applicability": false,
    "legal": true
  },
  "DECREE_A32_P3_S1_Ie": {
    "applicability": false,
    "legal": true
  },
  "DECREE_A32_P3_S1_If": {
    "applicability": false,
    "legal": true
  },
  "DECREE_A32_P3_S1_Ig": {
    "applicability": false,
    "legal": true
  },
  "DECREE_A32_P3_S1_Ih": {
    "applicability": false,
    "legal": true
  },
  "DECREE_A32_P3_S1_Io": {
    "applicability": false,
    "legal": true
  },
  "DECREE_A32_P3_S2": {
    "applicability": false,
    "legal": true
  },
  "DECREE_A32_P3_S2_Ia": {
    "applicability": false,
    "legal": true
  },
  "DECREE_A32_P3_S2_Ib": {
    "applicability": false,
    "legal": true
  },
  "DECREE_A32_P4": {
    "applicability": false,
    "legal": true
  },
  "DECREE_A32_P4_S1": {
    "applicability": false,
    "legal": true
  },
  "DECREE_A32_P4_S1_Ia": {
    "applicability": false,
    "legal": true
  },
  "DECREE_A32_P4_S1_Ib": {
    "applicability": false,
    "legal": true
  },
  "DECREE_A32_P4_S2": {
    "applicability": false,
    "legal": true
  },
  "DECREE_A32_P4_S3": {
    "applicability": false,
    "legal": true
  },
  "DECREE_A32_P4_S4": {
    "applicability": false,
    "legal": true
  },
  "DECREE_A32_P5": {
    "applicability": false,
    "legal": true
  },
  "DECREE_A32_P6": {
    "applicability": false,
    "legal": true
  },
  "DECREE_A32_P6_S1": {
    "applicability": false,
    "legal": true
  },
  "DECREE_A32_P6_S2": {
    "applicability": false,
    "legal": true
  },
  "DECREE_A32_P6_S3": {
    "applicability": false,
    "legal": true
  },
  "DECREE_A32_2": {
    "applicability": false,
    "legal": true
  },
  "DECREE_A32_2_P1": {
    "applicability": false,
    "legal": true
  },
  "DECREE_A32_2_P1_S1": {
    "applicability": false,
    "legal": true
  },
  "DECREE_A32_2_P1_S2": {
    "applicability": false,
    "legal": true
  },
  "DECREE_A32_2_P1_S3": {
    "applicability": false,
    "legal": true
  },
  "DECREE_A32_2_P1_S4": {
    "applicability": false,
    "legal": true
  },
  "DECREE_A32_2_P1_S5": {
    "applicability": false,
    "legal": true
  },
  "DECREE_A32_2_P1_S6": {
    "applicability": false,
    "legal": true
  },
  "DECREE_A32_2_P2": {
    "applicability": false,
    "legal": true
  },
  "DECREE_A32_3": {
    "applicability": true,
    "legal": false
  },
  "DECREE_A32_3_P1": {
    "applicability": false,
    "legal": false
  },
  "DECREE_A32_3_P1_S1": {
    "applicability": false,
    "legal": false
  },
  "DECREE_A32_3_P1_S2": {
    "applicability": false,
    "legal": false
  },
  "DECREE_A32_3_P1_S3": {
    "applicability": false,
    "legal": false
  },
  "DECREE_A32_3_P2": {
    "applicability": false,
    "legal": false
  },
  "DECREE_A33": {
    "applicability": false,
    "legal": true
  },
  "DECREE_A33_P1": {
    "applicability": false,
    "legal": true
  },
  "DECREE_A33_P1_S1": {
    "applicability": false,
    "legal": true
  },
  "DECREE_A33_P1_S2": {
    "applicability": false,
    "legal": true
  },
  "DECREE_A33_P1_S3": {
    "applicability": false,
    "legal": true
  },
  "DECREE_A33_P1_S4": {
    "applicability": false,
    "legal": true
  },
  "DECREE_A33_P1_S5": {
    "applicability": false,
    "legal": true
  },
  "DECREE_A33_P2": {
    "applicability": false,
    "legal": true
  },
  "DECREE_A33_P2_S1": {
    "applicability": false,
    "legal": true
  },
  "DECREE_A33_P2_S2": {
    "applicability": false,
    "legal": true
  },
  "DECREE_A33_P2_S3": {
    "applicability": false,
    "legal": true
  },
  "DECREE_A34": {
    "applicability": false,
    "legal": true
  },
  "DECREE_A34_P1": {
    "applicability": false,
    "legal": true
  },
  "DECREE_A34_P2": {
    "applicability": false,
    "legal": true
  },
  "DECREE_A34_P3": {
    "applicability": false,
    "legal": true
  },
  "DECREE_A34_2": {
    "applicability": false,
    "legal": true
  },
  "DECREE_A34_2_P1": {
    "applicability": false,
    "legal": true
  },
  "DECREE_A34_2_P2": {
    "applicability": false,
    "legal": true
  },
  "DECREE_A34_2_P2_S1": {
    "applicability": false,
    "legal": true
  },
  "DECREE_A34_2_P2_S2": {
    "applicability": false,
    "legal": true
  },
  "DECREE_A34_2_P2_S3": {
    "applicability": false,
    "legal": true
  },
  "DECREE_A34_2_P3": {
    "applicability": false,
    "legal": true
  },
  "DECREE_A34_2_P4": {
    "applicability": false,
    "legal": true
  },
  "DECREE_A34_2_P5": {
    "applicability": false,
    "legal": true
  },
  "DECREE_A34_2_P6": {
    "applicability": false,
    "legal": true
  },
  "DECREE_A34_3": {
    "applicability": false,
    "legal": true
  },
  "DECREE_A34_3_P1": {
    "applicability": false,
    "legal": true
  },
  "DECREE_A34_3_P2": {
    "applicability": false,
    "legal": true
  },
  "DECREE_A34_4": {
    "applicability": false,
    "legal": true
  },
  "DECREE_A34_4_P1": {
    "applicability": false,
    "legal": true
  },
  "DECREE_A34_4_P2": {
    "applicability": false,
    "legal": true
  },
  "DECREE_A34_5": {
    "applicability": false,
    "legal": true
  },
  "DECREE_A34_5_P1": {
    "applicability": false,
    "legal": true
  },
  "DECREE_A34_5_P2": {
    "applicability": false,
    "legal": true
  },
  "DECREE_A34_6": {
    "applicability": false,
    "legal": true
  },
  "DECREE_A34_6_P1": {
    "applicability": false,
    "legal": true
  },
  "DECREE_A34_6_P1_S1": {
    "applicability": false,
    "legal": true
  },
  "DECREE_A34_6_P1_S2": {
    "applicability": false,
    "legal": true
  },
  "DECREE_A34_6_P1_S2_Ia": {
    "applicability": false,
    "legal": true
  },
  "DECREE_A34_6_P1_S2_Ib": {
    "applicability": false,
    "legal": true
  },
  "DECREE_A34_6_P2": {
    "applicability": false,
    "legal": true
  },
  "DECREE_A34_7": {
    "applicability": false,
    "legal": true
  },
  "DECREE_A34_8": {
    "applicability": false,
    "legal": true
  },
  "DECREE_A34_8_P1": {
    "applicability": false,
    "legal": true
  },
  "DECREE_A34_8_P2": {
    "applicability": false,
    "legal": true
  },
  "DECREE_A34_8_P2_S1": {
    "applicability": false,
    "legal": true
  },
  "DECREE_A34_8_P2_S2": {
    "applicability": false,
    "legal": true
  },
  "DECREE_A34_8_P2_S3": {
    "applicability": false,
    "legal": true
  },
  "DECREE_A34_8_P3": {
    "applicability": false,
    "legal": true
  },
  "DECREE_A35": {
    "applicability": false,
    "legal": true
  },
  "DECREE_A35_S1": {
    "applicability": false,
    "legal": true
  },
  "DECREE_A35_S2": {
    "applicability": false,
    "legal": true
  },
  "DECREE_A35_S3": {
    "applicability": false,
    "legal": true
  },
  "DECREE_A35_S4": {
    "applicability": false,
    "legal": true
  },
  "DECREE_A36": {
    "applicability": false,
    "legal": true
  },
  "DECREE_A36_P1": {
    "applicability": false,
    "legal": true
  },
  "DECREE_A36_P1_S1": {
    "applicability": false,
    "legal": true
  },
  "DECREE_A36_P1_S1_Ia": {
    "applicability": false,
    "legal": true
  },
  "DECREE_A36_P1_S1_Ib": {
    "applicability": false,
    "legal": true
  },
  "DECREE_A36_P1_S1_Ic": {
    "applicability": false,
    "legal": true
  },
  "DECREE_A36_P1_S1_Id": {
    "applicability": false,
    "legal": true
  },
  "DECREE_A36_P1_S1_Ie": {
    "applicability": false,
    "legal": true
  },
  "DECREE_A36_P1_S2": {
    "applicability": false,
    "legal": true
  },
  "DECREE_A36_P1_S3": {
    "applicability": false,
    "legal": true
  },
  "DECREE_A36_P1_S3_Ia": {
    "applicability": false,
    "legal": true
  },
  "DECREE_A36_P1_S3_Ib": {
    "applicability": false,
    "legal": true
  },
  "DECREE_A36_P2": {
    "applicability": false,
    "legal": true
  },
  "DECREE_A36_P2_S1": {
    "applicability": false,
    "legal": true
  },
  "DECREE_A36_P2_S2": {
    "applicability": false,
    "legal": true
  },
  "DECREE_A36_P2_S3": {
    "applicability": false,
    "legal": true
  },
  "DECREE_A36_P2_S4": {
    "applicability": false,
    "legal": true
  },
  "DECREE_A36_P3": {
    "applicability": false,
    "legal": true
  },
  "DECREE_A36_P3_S1": {
    "applicability": false,
    "legal": true
  },
  "DECREE_A36_P3_S2": {
    "applicability": false,
    "legal": true
  },
  "DECREE_A36_P4": {
    "applicability": false,
    "legal": true
  },
  "DECREE_A36_P4_S1": {
    "applicability": false,
    "legal": true
  },
  "DECREE_A36_P4_S2": {
    "applicability": false,
    "legal": true
  },
  "DECREE_A36_P5": {
    "applicability": false,
    "legal": true
  },
  "DECREE_A36_P5_S1": {
    "applicability": false,
    "legal": true
  },
  "DECREE_A36_P5_S2": {
    "applicability": false,
    "legal": true
  },
  "DECREE_A36_P5_S3": {
    "applicability": false,
    "legal": true
  },
  "DECREE_A36_P5_S4": {
    "applicability": false,
    "legal": true
  },
  "DECREE_A36_P6": {
    "applicability": false,
    "legal": true
  },
  "DECREE_A36_P6_S1": {
    "applicability": false,
    "legal": true
  },
  "DECREE_A36_P6_S2": {
    "applicability": false,
    "legal": true
  },
  "DECREE_A36_P6_S3": {
    "applicability": false,
    "legal": true
  },
  "DECREE_A36_P7": {
    "applicability": false,
    "legal": true
  },
  "DECREE_A37": {
    "applicability": false,
    "legal": true
  },
  "DECREE_A37_S1": {
    "applicability": false,
    "legal": true
  },
  "DECREE_A37_S2": {
    "applicability": false,
    "legal": true
  },
  "DECREE_A38": {
    "applicability": false,
    "legal": true
  },
  "DECREE_A38_P1": {
    "applicability": false,
    "legal": true
  },
  "DECREE_A38_P1_S1": {
    "applicability": false,
    "legal": true
  },
  "DECREE_A38_P1_S2": {
    "applicability": false,
    "legal": true
  },
  "DECREE_A38_P1_S3": {
    "applicability": false,
    "legal": true
  },
  "DECREE_A38_P1_S4": {
    "applicability": false,
    "legal": true
  },
  "DECREE_A38_P2": {
    "applicability": false,
    "legal": true
  },
  "DECREE_A38_P2_S1": {
    "applicability": false,
    "legal": true
  },
  "DECREE_A38_P2_S2": {
    "applicability": false,
    "legal": true
  },
  "DECREE_A38_P2_S3": {
    "applicability": false,
    "legal": true
  },
  "DECREE_A38_P2_S4": {
    "applicability": false,
    "legal": true
  },
  "DECREE_A38_P2_S5": {
    "applicability": false,
    "legal": true
  },
  "DECREE_A38_P2_S6": {
    "applicability": false,
    "legal": true
  },
  "DECREE_A38_P3": {
    "applicability": false,
    "legal": true
  },
  "DECREE_A38_P4": {
    "applicability": false,
    "legal": true
  },
  "DECREE_A39": {
    "applicability": true,
    "legal": true
  },
  "DECREE_A39_P1": {
    "applicability": true,
    "legal": true
  },
  "DECREE_A39_P1_S1": {
    "applicability": false,
    "legal": false
  },
  "DECREE_A39_P1_S2": {
    "applicability": false,
    "legal": false
  },
  "DECREE_A39_P2": {
    "applicability": false,
    "legal": true
  },
  "DECREE_A39_P3": {
    "applicability": true,
    "legal": false
  },
  "DECREE_A40": {
    "applicability": false,
    "legal": false
  },
  "DECREE_A40_P1": {
    "applicability": false,
    "legal": true
  },
  "DECREE_A40_P1_S1": {
    "applicability": false,
    "legal": false
  },
  "DECREE_A40_P1_S2": {
    "applicability": false,
    "legal": false
  },
  "DECREE_A40_P1_S3": {
    "applicability": false,
    "legal": false
  },
  "DECREE_A40_P2": {
    "applicability": false,
    "legal": false
  },
  "DECREE_A40_P3": {
    "applicability": false,
    "legal": false
  },
  "DECREE_A40_2": {
    "applicability": false,
    "legal": true
  },
  "DECREE_C6": {
    "applicability": false,
    "legal": true
  },
  "DECREE_A41": {
    "applicability": true,
    "legal": false
  },
  "DECREE_A41_P1": {
    "applicability": false,
    "legal": false
  },
  "DECREE_A41_P1_S1": {
    "applicability": false,
    "legal": false
  },
  "DECREE_A41_P1_S2": {
    "applicability": false,
    "legal": false
  },
  "DECREE_A41_P1_S3": {
    "applicability": false,
    "legal": false
  },
  "DECREE_A41_P1_S4": {
    "applicability": false,
    "legal": false
  },
  "DECREE_A41_P1_S5": {
    "applicability": false,
    "legal": false
  },
  "DECREE_A41_P2": {
    "applicability": true,
    "legal": false
  },
  "DECREE_A41_P2_S1": {
    "applicability": true,
    "legal": false
  },
  "DECREE_A41_P2_S2": {
    "applicability": true,
    "legal": false
  },
  "DECREE_A41_P2_S3": {
    "applicability": false,
    "legal": false
  },
  "DECREE_A41_P3": {
    "applicability": false,
    "legal": false
  },
  "DECREE_A41_P4": {
    "applicability": false,
    "legal": false
  },
  "DECREE_A41_P5": {
    "applicability": false,
    "legal": false
  },
  "DECREE_A42": {
    "applicability": false,
    "legal": false
  },
  "DECREE_A42_P1": {
    "applicability": false,
    "legal": false
  },
  "DECREE_A42_P2": {
    "applicability": false,
    "legal": false
  },
  "DECREE_A42_2": {
    "applicability": false,
    "legal": true
  },
  "DECREE_A42_2_S1": {
    "applicability": false,
    "legal": true
  },
  "DECREE_A42_2_S1_Ia": {
    "applicability": false,
    "legal": true
  },
  "DECREE_A42_2_S1_Ib": {
    "applicability": false,
    "legal": true
  },
  "DECREE_A42_2_S1_Ic": {
    "applicability": false,
    "legal": true
  },
  "DECREE_A42_2_S1_Id": {
    "applicability": false,
    "legal": true
  },
  "DECREE_A42_2_S2": {
    "applicability": false,
    "legal": true
  },
  "DECREE_A42_2_S2_Ia": {
    "applicability": false,
    "legal": true
  },
  "DECREE_A42_2_S2_Ib": {
    "applicability": false,
    "legal": true
  },
  "DECREE_A42_2_S3": {
    "applicability": false,
    "legal": true
  },
  "DECREE_A42_2_S3_Ia": {
    "applicability": false,
    "legal": true
  },
  "DECREE_A42_2_S3_Ib": {
    "applicability": false,
    "legal": true
  },
  "DECREE_A42_3": {
    "applicability": false,
    "legal": true
  },
  "DECREE_A42_3_P1": {
    "applicability": false,
    "legal": true
  },
  "DECREE_A42_3_P1_S1": {
    "applicability": false,
    "legal": true
  },
  "DECREE_A42_3_P1_S2": {
    "applicability": false,
    "legal": true
  },
  "DECREE_A42_3_P1_S3": {
    "applicability": false,
    "legal": true
  },
  "DECREE_A42_3_P1_S4": {
    "applicability": false,
    "legal": true
  },
  "DECREE_A42_3_P2": {
    "applicability": false,
    "legal": true
  },
  "DECREE_A42_4": {
    "applicability": false,
    "legal": true
  },
  "DECREE_A42_4_P1": {
    "applicability": false,
    "legal": true
  },
  "DECREE_A42_4_P1_S1": {
    "applicability": false,
    "legal": true
  },
  "DECREE_A42_4_P1_S1_Ia": {
    "applicability": false,
    "legal": true
  },
  "DECREE_A42_4_P1_S1_Ib": {
    "applicability": false,
    "legal": true
  },
  "DECREE_A42_4_P1_S1_Ic": {
    "applicability": false,
    "legal": true
  },
  "DECREE_A42_4_P1_S1_Id": {
    "applicability": false,
    "legal": true
  },
  "DECREE_A42_4_P1_S2": {
    "applicability": false,
    "legal": true
  },
  "DECREE_A42_4_P1_S3": {
    "applicability": false,
    "legal": true
  },
  "DECREE_A42_4_P1_S3_Ia": {
    "applicability": false,
    "legal": true
  },
  "DECREE_A42_4_P1_S3_Ib": {
    "applicability": false,
    "legal": true
  },
  "DECREE_A42_4_P1_S3_Ic": {
    "applicability": false,
    "legal": true
  },
  "DECREE_A42_4_P2": {
    "applicability": false,
    "legal": true
  },
  "DECREE_A42_4_P3": {
    "applicability": false,
    "legal": true
  },
  "DECREE_A42_4_P4": {
    "applicability": false,
    "legal": true
  },
  "DECREE_A42_5": {
    "applicability": false,
    "legal": true
  },
  "DECREE_A42_5_P1": {
    "applicability": false,
    "legal": true
  },
  "DECREE_A42_5_P2": {
    "applicability": false,
    "legal": true
  },
  "DECREE_A42_5_P2_S1": {
    "applicability": false,
    "legal": true
  },
  "DECREE_A42_5_P2_S2": {
    "applicability": false,
    "legal": true
  },
  "DECREE_A42_5_P2_S3": {
    "applicability": false,
    "legal": true
  },
  "DECREE_A42_5_P2_S4": {
    "applicability": false,
    "legal": true
  },
  "DECREE_A42_5_P2_S5": {
    "applicability": false,
    "legal": true
  },
  "DECREE_A42_5_P2_S6": {
    "applicability": false,
    "legal": true
  },
  "DECREE_A42_5_P2_S7": {
    "applicability": false,
    "legal": true
  },
  "DECREE_A42_5_P3": {
    "applicability": false,
    "legal": true
  },
  "DECREE_A42_5_P4": {
    "applicability": false,
    "legal": true
  },
  "DECREE_A42_5_P5": {
    "applicability": false,
    "legal": true
  },
  "DECREE_A42_6": {
    "applicability": false,
    "legal": true
  },
  "DECREE_A42_6_P1": {
    "applicability": false,
    "legal": true
  },
  "DECREE_A42_6_P2": {
    "applicability": false,
    "legal": true
  },
  "DECREE_A42_6_P3": {
    "applicability": false,
    "legal": true
  },
  "DECREE_A42_6_P3_S1": {
    "applicability": false,
    "legal": true
  },
  "DECREE_A42_6_P3_S2": {
    "applicability": false,
    "legal": true
  },
  "DECREE_A42_6_P3_S3": {
    "applicability": false,
    "legal": true
  },
  "DECREE_A42_6_P3_S4": {
    "applicability": false,
    "legal": true
  },
  "DECREE_A42_6_P4": {
    "applicability": false,
    "legal": true
  },
  "DECREE_A42_6_P5": {
    "applicability": false,
    "legal": true
  },
  "DECREE_A42_6_P6": {
    "applicability": false,
    "legal": true
  },
  "DECREE_A42_6_P6_S1": {
    "applicability": false,
    "legal": true
  },
  "DECREE_A42_6_P6_S2": {
    "applicability": false,
    "legal": true
  },
  "DECREE_A42_6_P6_S3": {
    "applicability": false,
    "legal": true
  },
  "DECREE_A42_6_P6_S4": {
    "applicability": false,
    "legal": true
  },
  "DECREE_A42_6_P6_S5": {
    "applicability": false,
    "legal": true
  },
  "DECREE_A42_6_P6_S6": {
    "applicability": false,
    "legal": true
  },
  "DECREE_A42_6_P6_S7": {
    "applicability": false,
    "legal": true
  },
  "DECREE_A42_6_P6_S8": {
    "applicability": false,
    "legal": true
  },
  "DECREE_A42_6_P7": {
    "applicability": false,
    "legal": true
  },
  "DECREE_A42_6_P7_S1": {
    "applicability": false,
    "legal": true
  },
  "DECREE_A42_6_P7_S1_Ia": {
    "applicability": false,
    "legal": true
  },
  "DECREE_A42_6_P7_S1_Ib": {
    "applicability": false,
    "legal": true
  },
  "DECREE_A42_6_P7_S1_Ic": {
    "applicability": false,
    "legal": true
  },
  "DECREE_A42_6_P7_S2": {
    "applicability": false,
    "legal": true
  },
  "DECREE_A42_6_P7_S2_Ia": {
    "applicability": false,
    "legal": true
  },
  "DECREE_A42_6_P7_S2_Ib": {
    "applicability": false,
    "legal": true
  },
  "DECREE_A42_6_P7_S2_Ic": {
    "applicability": false,
    "legal": true
  },
  "DECREE_A42_6_P8": {
    "applicability": false,
    "legal": true
  },
  "DECREE_A42_6_P9": {
    "applicability": false,
    "legal": true
  },
  "DECREE_A42_6_P9_S1": {
    "applicability": false,
    "legal": true
  },
  "DECREE_A42_6_P9_S2": {
    "applicability": false,
    "legal": true
  },
  "DECREE_A42_6_P9_S3": {
    "applicability": false,
    "legal": true
  },
  "DECREE_A42_6_P10": {
    "applicability": false,
    "legal": true
  },
  "DECREE_A42_6_P11": {
    "applicability": false,
    "legal": true
  },
  "DECREE_A42_7": {
    "applicability": false,
    "legal": true
  },
  "DECREE_A42_7_S1": {
    "applicability": false,
    "legal": true
  },
  "DECREE_A42_7_S2": {
    "applicability": false,
    "legal": true
  },
  "DECREE_A42_7_S3": {
    "applicability": false,
    "legal": true
  },
  "DECREE_A42_7_S4": {
    "applicability": false,
    "legal": true
  },
  "DECREE_A42_7_S5": {
    "applicability": false,
    "legal": true
  },
  "DECREE_A42_7_S6": {
    "applicability": false,
    "legal": true
  },
  "DECREE_A42_7_S7": {
    "applicability": false,
    "legal": true
  },
  "DECREE_A42_7_S8": {
    "applicability": false,
    "legal": true
  },
  "DECREE_A42_7_S9": {
    "applicability": false,
    "legal": true
  },
  "DECREE_A42_7_S10": {
    "applicability": false,
    "legal": true
  },
  "DECREE_A42_7_S11": {
    "applicability": false,
    "legal": true
  },
  "DECREE_A42_7_S12": {
    "applicability": false,
    "legal": true
  },
  "DECREE_A42_8": {
    "applicability": false,
    "legal": true
  },
  "DECREE_A42_8_P1": {
    "applicability": false,
    "legal": true
  },
  "DECREE_A42_8_P1_S1": {
    "applicability": false,
    "legal": true
  },
  "DECREE_A42_8_P1_S2": {
    "applicability": false,
    "legal": true
  },
  "DECREE_A42_8_P1_S3": {
    "applicability": false,
    "legal": true
  },
  "DECREE_A42_8_P1_S4": {
    "applicability": false,
    "legal": true
  },
  "DECREE_A42_8_P1_S5": {
    "applicability": false,
    "legal": true
  },
  "DECREE_A42_8_P1_S6": {
    "applicability": false,
    "legal": true
  },
  "DECREE_A42_8_P1_S7": {
    "applicability": false,
    "legal": true
  },
  "DECREE_A42_8_P1_S8": {
    "applicability": false,
    "legal": true
  },
  "DECREE_A42_8_P1_S9": {
    "applicability": false,
    "legal": true
  },
  "DECREE_A42_8_P1_S10": {
    "applicability": false,
    "legal": true
  },
  "DECREE_A42_8_P1_S11": {
    "applicability": false,
    "legal": true
  },
  "DECREE_A42_8_P2": {
    "applicability": false,
    "legal": true
  },
  "DECREE_A42_9": {
    "applicability": false,
    "legal": true
  },
  "DECREE_A42_9_P1": {
    "applicability": false,
    "legal": true
  },
  "DECREE_A42_9_P1_S1": {
    "applicability": false,
    "legal": true
  },
  "DECREE_A42_9_P1_S2": {
    "applicability": false,
    "legal": true
  },
  "DECREE_A42_9_P1_S3": {
    "applicability": false,
    "legal": true
  },
  "DECREE_A42_9_P2": {
    "applicability": false,
    "legal": true
  },
  "DECREE_A42_9_P3": {
    "applicability": false,
    "legal": true
  },
  "DECREE_A42_9_P4": {
    "applicability": false,
    "legal": true
  },
  "DECREE_A42_10": {
    "applicability": false,
    "legal": true
  },
  "DECREE_A42_10_P1": {
    "applicability": false,
    "legal": true
  },
  "DECREE_A42_10_P1_S1": {
    "applicability": false,
    "legal": true
  },
  "DECREE_A42_10_P1_S2": {
    "applicability": false,
    "legal": true
  },
  "DECREE_A42_10_P1_S3": {
    "applicability": false,
    "legal": true
  },
  "DECREE_A42_10_P1_S4": {
    "applicability": false,
    "legal": true
  },
  "DECREE_A42_10_P1_S5": {
    "applicability": false,
    "legal": true
  },
  "DECREE_A42_10_P1_S6": {
    "applicability": false,
    "legal": true
  },
  "DECREE_A42_10_P2": {
    "applicability": false,
    "legal": true
  },
  "DECREE_A42_10_P2_S1": {
    "applicability": false,
    "legal": true
  },
  "DECREE_A42_10_P2_S2": {
    "applicability": false,
    "legal": true
  },
  "DECREE_A42_10_P2_S3": {
    "applicability": false,
    "legal": true
  },
  "DECREE_A42_10_P3": {
    "applicability": false,
    "legal": true
  },
  "DECREE_A42_10_P4": {
    "applicability": false,
    "legal": true
  },
  "DECREE_A42_11": {
    "applicability": false,
    "legal": true
  },
  "DECREE_A42_11_P1": {
    "applicability": false,
    "legal": true
  },
  "DECREE_A42_11_P1_S1": {
    "applicability": false,
    "legal": true
  },
  "DECREE_A42_11_P1_S1_Ia": {
    "applicability": false,
    "legal": true
  },
  "DECREE_A42_11_P1_S1_Ib": {
    "applicability": false,
    "legal": true
  },
  "DECREE_A42_11_P1_S1_Ic": {
    "applicability": false,
    "legal": true
  },
  "DECREE_A42_11_P1_S2": {
    "applicability": false,
    "legal": true
  },
  "DECREE_A42_11_P1_S2_Ia": {
    "applicability": false,
    "legal": true
  },
  "DECREE_A42_11_P1_S2_Ib": {
    "applicability": false,
    "legal": true
  },
  "DECREE_A42_11_P1_S3": {
    "applicability": false,
    "legal": true
  },
  "DECREE_A42_11_P1_S3_Ia": {
    "applicability": false,
    "legal": true
  },
  "DECREE_A42_11_P1_S3_Ib": {
    "applicability": false,
    "legal": true
  },
  "DECREE_A42_11_P1_S3_Ic": {
    "applicability": false,
    "legal": true
  },
  "DECREE_A42_11_P2": {
    "applicability": false,
    "legal": true
  },
  "DECREE_A42_11_P2_S1": {
    "applicability": false,
    "legal": true
  },
  "DECREE_A42_11_P2_S2": {
    "applicability": false,
    "legal": true
  },
  "DECREE_A42_11_P2_S3": {
    "applicability": false,
    "legal": true
  },
  "DECREE_A42_12": {
    "applicability": false,
    "legal": true
  },
  "DECREE_A42_12_P1": {
    "applicability": false,
    "legal": true
  },
  "DECREE_A42_12_P2": {
    "applicability": false,
    "legal": true
  },
  "DECREE_A42_12_P2_S1": {
    "applicability": false,
    "legal": true
  },
  "DECREE_A42_12_P2_S2": {
    "applicability": false,
    "legal": true
  },
  "DECREE_A42_12_P3": {
    "applicability": false,
    "legal": true
  },
  "DECREE_A42_12_P4": {
    "applicability": false,
    "legal": true
  },
  "DECREE_A42_12_P5": {
    "applicability": false,
    "legal": true
  },
  "DECREE_A42_12_P5_S1": {
    "applicability": false,
    "legal": true
  },
  "DECREE_A42_12_P5_S2": {
    "applicability": false,
    "legal": true
  },
  "DECREE_A42_12_P6": {
    "applicability": false,
    "legal": true
  },
  "DECREE_A42_12_P6_S1": {
    "applicability": false,
    "legal": true
  },
  "DECREE_A42_12_P6_S2": {
    "applicability": false,
    "legal": true
  },
  "DECREE_A42_12_P7": {
    "applicability": false,
    "legal": true
  },
  "DECREE_A42_12_P7_S1": {
    "applicability": false,
    "legal": true
  },
  "DECREE_A42_12_P7_S2": {
    "applicability": false,
    "legal": true
  },
  "DECREE_A42_12_P7_S3": {
    "applicability": false,
    "legal": true
  },
  "DECREE_A42_12_P7_S3_Ia": {
    "applicability": false,
    "legal": true
  },
  "DECREE_A42_12_P7_S3_Ib": {
    "applicability": false,
    "legal": true
  },
  "DECREE_A42_12_P7_S3_Ic": {
    "applicability": false,
    "legal": true
  },
  "DECREE_A42_12_P8": {
    "applicability": false,
    "legal": true
  },
  "DECREE_A42_13": {
    "applicability": false,
    "legal": true
  },
  "DECREE_A42_14": {
    "applicability": false,
    "legal": true
  },
  "DECREE_A42_14_P1": {
    "applicability": false,
    "legal": true
  },
  "DECREE_A42_14_P2": {
    "applicability": false,
    "legal": true
  },
  "DECREE_A42_14_P3": {
    "applicability": false,
    "legal": true
  },
  "DECREE_A42_14_P3_S1": {
    "applicability": false,
    "legal": true
  },
  "DECREE_A42_14_P3_S2": {
    "applicability": false,
    "legal": true
  },
  "DECREE_A42_15": {
    "applicability": false,
    "legal": true
  },
  "DECREE_A42_15_P1": {
    "applicability": false,
    "legal": true
  },
  "DECREE_A42_15_P2": {
    "applicability": false,
    "legal": true
  },
  "DECREE_A42_15_P2_S1": {
    "applicability": false,
    "legal": true
  },
  "DECREE_A42_15_P2_S2": {
    "applicability": false,
    "legal": true
  },
  "DECREE_A42_15_P2_S2_Ia": {
    "applicability": false,
    "legal": true
  },
  "DECREE_A42_15_P2_S2_Ib": {
    "applicability": false,
    "legal": true
  },
  "DECREE_A42_15_P2_S2_Ic": {
    "applicability": false,
    "legal": true
  },
  "DECREE_A42_15_P2_S2_Id": {
    "applicability": false,
    "legal": true
  },
  "DECREE_A42_15_P2_S3": {
    "applicability": false,
    "legal": true
  },
  "DECREE_A42_15_P2_S3_Ia": {
    "applicability": false,
    "legal": true
  },
  "DECREE_A42_15_P2_S3_Ib": {
    "applicability": false,
    "legal": true
  },
  "DECREE_A42_15_P2_S3_Ic": {
    "applicability": false,
    "legal": true
  },
  "DECREE_A42_16": {
    "applicability": false,
    "legal": true
  },
  "DECREE_A42_16_P1": {
    "applicability": false,
    "legal": true
  },
  "DECREE_A42_16_P2": {
    "applicability": false,
    "legal": true
  },
  "DECREE_A42_16_P2_S1": {
    "applicability": false,
    "legal": true
  },
  "DECREE_A42_16_P2_S2": {
    "applicability": false,
    "legal": true
  },
  "DECREE_A42_16_P3": {
    "applicability": false,
    "legal": true
  },
  "DECREE_A43": {
    "applicability": false,
    "legal": true
  },
  "DECREE_A43_P1": {
    "applicability": false,
    "legal": true
  },
  "DECREE_A43_P2": {
    "applicability": false,
    "legal": true
  },
  "DECREE_A43_P3": {
    "applicability": false,
    "legal": true
  },
  "DECREE_A44": {
    "applicability": false,
    "legal": true
  },
  "DECREE_A44_P1": {
    "applicability": false,
    "legal": true
  },
  "DECREE_A44_P2": {
    "applicability": false,
    "legal": true
  },
  "DECREE_A44_2": {
    "applicability": false,
    "legal": true
  },
  "DECREE_A44_2_P1": {
    "applicability": false,
    "legal": true
  },
  "DECREE_A44_2_P2": {
    "applicability": false,
    "legal": true
  },
  "DECREE_A44_2_P2_S1": {
    "applicability": false,
    "legal": true
  },
  "DECREE_A44_2_P2_S2": {
    "applicability": false,
    "legal": true
  },
  "DECREE_A44_2_P3": {
    "applicability": false,
    "legal": true
  },
  "DECREE_A44_3": {
    "applicability": false,
    "legal": true
  },
  "DECREE_A44_3_P1": {
    "applicability": false,
    "legal": true
  },
  "DECREE_A44_3_P1_S1": {
    "applicability": false,
    "legal": true
  },
  "DECREE_A44_3_P1_S2": {
    "applicability": false,
    "legal": true
  },
  "DECREE_A44_3_P2": {
    "applicability": false,
    "legal": true
  },
  "DECREE_A44_3_P2_S1": {
    "applicability": false,
    "legal": true
  },
  "DECREE_A44_3_P2_S2": {
    "applicability": false,
    "legal": true
  },
  "DECREE_A44_3_P2_S3": {
    "applicability": false,
    "legal": true
  },
  "DECREE_A44_3_P2_S4": {
    "applicability": false,
    "legal": true
  },
  "DECREE_A44_3_P3": {
    "applicability": false,
    "legal": true
  },
  "DECREE_A44_3_P4": {
    "applicability": false,
    "legal": true
  },
  "DECREE_A44_3_P5": {
    "applicability": false,
    "legal": true
  },
  "DECREE_A44_3_P6": {
    "applicability": false,
    "legal": true
  },
  "DECREE_A44_4": {
    "applicability": false,
    "legal": true
  },
  "DECREE_A44_4_P1": {
    "applicability": false,
    "legal": true
  },
  "DECREE_A44_4_P1_S1": {
    "applicability": false,
    "legal": true
  },
  "DECREE_A44_4_P1_S2": {
    "applicability": false,
    "legal": true
  },
  "DECREE_A44_4_P1_S3": {
    "applicability": false,
    "legal": true
  },
  "DECREE_A44_4_P1_S4": {
    "applicability": false,
    "legal": true
  },
  "DECREE_A44_4_P1_S5": {
    "applicability": false,
    "legal": true
  },
  "DECREE_A44_4_P2": {
    "applicability": false,
    "legal": true
  },
  "DECREE_A45": {
    "applicability": false,
    "legal": true
  },
  "DECREE_A45_P1": {
    "applicability": false,
    "legal": true
  },
  "DECREE_A45_P1_S1": {
    "applicability": false,
    "legal": true
  },
  "DECREE_A45_P1_S2": {
    "applicability": false,
    "legal": true
  },
  "DECREE_A45_P2": {
    "applicability": false,
    "legal": true
  },
  "DECREE_A46": {
    "applicability": false,
    "legal": true
  },
  "DECREE_A46_P1": {
    "applicability": false,
    "legal": true
  },
  "DECREE_A46_P2": {
    "applicability": false,
    "legal": true
  },
  "DECREE_A46_P3": {
    "applicability": false,
    "legal": true
  },
  "DECREE_A47": {
    "applicability": false,
    "legal": true
  },
  "DECREE_A47_P1": {
    "applicability": false,
    "legal": true
  },
  "DECREE_A47_P2": {
    "applicability": false,
    "legal": true
  },
  "DECREE_A47_P3": {
    "applicability": false,
    "legal": true
  },
  "DECREE_A47_P3_S1": {
    "applicability": false,
    "legal": true
  },
  "DECREE_A47_P3_S2": {
    "applicability": false,
    "legal": true
  },
  "DECREE_A47_P3_S3": {
    "applicability": false,
    "legal": true
  },
  "DECREE_A47_P4": {
    "applicability": false,
    "legal": true
  },
  "DECREE_A48": {
    "applicability": false,
    "legal": true
  },
  "DECREE_A48_P1": {
    "applicability": false,
    "legal": true
  },
  "DECREE_A48_P2": {
    "applicability": false,
    "legal": true
  },
  "DECREE_A48_7": {
    "applicability": false,
    "legal": true
  },
  "DECREE_A48_7_P1": {
    "applicability": false,
    "legal": true
  },
  "DECREE_A48_7_P1_S1": {
    "applicability": false,
    "legal": true
  },
  "DECREE_A48_7_P1_S2": {
    "applicability": false,
    "legal": true
  },
  "DECREE_A48_7_P2": {
    "applicability": false,
    "legal": true
  },
  "DECREE_A48_7_P2_S1": {
    "applicability": false,
    "legal": true
  },
  "DECREE_A48_7_P2_S2": {
    "applicability": false,
    "legal": true
  },
  "DECREE_A48_7_P2_S3": {
    "applicability": false,
    "legal": true
  },
  "DECREE_A48_7_P3": {
    "applicability": false,
    "legal": true
  },
  "DECREE_A48_7_P3_S1": {
    "applicability": false,
    "legal": true
  },
  "DECREE_A48_7_P3_S2": {
    "applicability": false,
    "legal": true
  },
  "DECREE_A48_7_P4": {
    "applicability": false,
    "legal": true
  },
  "DECREE_C7": {
    "applicability": false,
    "legal": true
  },
  "DECREE_A48_14": {
    "applicability": false,
    "legal": true
  },
  "DECREE_A49": {
    "applicability": false,
    "legal": true
  },
  "DECREE_A49_P1": {
    "applicability": false,
    "legal": true
  },
  "DECREE_A49_P2": {
    "applicability": false,
    "legal": true
  },
  "DECREE_A49_P3": {
    "applicability": false,
    "legal": true
  },
  "DECREE_A49_P4": {
    "applicability": false,
    "legal": true
  },
  "DECREE_A49_P5": {
    "applicability": false,
    "legal": true
  },
  "DECREE_A49_2": {
    "applicability": false,
    "legal": true
  },
  "DECREE_A49_2_P1": {
    "applicability": false,
    "legal": true
  },
  "DECREE_A49_2_P2": {
    "applicability": false,
    "legal": true
  },
  "DECREE_A49_2_P3": {
    "applicability": false,
    "legal": true
  },
  "DECREE_A49_2_P3_S1": {
    "applicability": false,
    "legal": true
  },
  "DECREE_A49_2_P3_S2": {
    "applicability": false,
    "legal": true
  },
  "DECREE_A49_2_P3_S3": {
    "applicability": false,
    "legal": true
  },
  "DECREE_A49_2_P3_S4": {
    "applicability": false,
    "legal": true
  },
  "DECREE_A49_2_P3_S5": {
    "applicability": false,
    "legal": true
  },
  "DECREE_A49_2_P3_S6": {
    "applicability": false,
    "legal": true
  },
  "DECREE_A49_2_P4": {
    "applicability": false,
    "legal": true
  },
  "DECREE_A50": {
    "applicability": false,
    "legal": true
  },
  "DECREE_A50_P1": {
    "applicability": false,
    "legal": true
  },
  "DECREE_A50_P2": {
    "applicability": false,
    "legal": true
  },
  "DECREE_A51": {
    "applicability": false,
    "legal": true
  },
  "DECREE_A51_P1": {
    "applicability": false,
    "legal": true
  },
  "DECREE_A51_P2": {
    "applicability": false,
    "legal": true
  },
  "DECREE_A51_P3": {
    "applicability": false,
    "legal": true
  },
  "DECREE_A51_2": {
    "applicability": false,
    "legal": true
  },
  "DECREE_A51_3": {
    "applicability": false,
    "legal": true
  },
  "DECREE_A51_3_P1": {
    "applicability": false,
    "legal": true
  },
  "DECREE_A51_3_P2": {
    "applicability": false,
    "legal": true
  },
  "DECREE_A51_3_P2_S1": {
    "applicability": false,
    "legal": true
  },
  "DECREE_A51_3_P2_S2": {
    "applicability": false,
    "legal": true
  },
  "DECREE_A51_3_P2_S3": {
    "applicability": false,
    "legal": true
  },
  "DECREE_A51_3_P2_S4": {
    "applicability": false,
    "legal": true
  },
  "DECREE_A51_3_P2_S5": {
    "applicability": false,
    "legal": true
  },
  "DECREE_A51_3_P2_S6": {
    "applicability": false,
    "legal": true
  },
  "DECREE_A51_3_P2_S7": {
    "applicability": false,
    "legal": true
  },
  "DECREE_A51_3_P3": {
    "applicability": false,
    "legal": true
  },
  "DECREE_A51_3_P4": {
    "applicability": false,
    "legal": true
  },
  "DECREE_A51_4": {
    "applicability": false,
    "legal": true
  },
  "DECREE_A51_4_P1": {
    "applicability": false,
    "legal": true
  },
  "DECREE_A51_4_P2": {
    "applicability": false,
    "legal": true
  },
  "DECREE_A52": {
    "applicability": false,
    "legal": true
  },
  "DECREE_A52_S1": {
    "applicability": false,
    "legal": true
  },
  "DECREE_A52_S1_Ia": {
    "applicability": false,
    "legal": true
  },
  "DECREE_A52_S1_Ib": {
    "applicability": false,
    "legal": true
  },
  "DECREE_A52_S1_Ic": {
    "applicability": false,
    "legal": true
  },
  "DECREE_A52_S2": {
    "applicability": false,
    "legal": true
  },
  "DECREE_A53": {
    "applicability": false,
    "legal": true
  },
  "DECREE_A53_P1": {
    "applicability": false,
    "legal": true
  },
  "DECREE_A53_P2": {
    "applicability": false,
    "legal": true
  },
  "DECREE_A54": {
    "applicability": false,
    "legal": true
  },
  "DECREE_A54_P1": {
    "applicability": false,
    "legal": true
  },
  "DECREE_A54_P2": {
    "applicability": false,
    "legal": true
  },
  "DECREE_A55": {
    "applicability": false,
    "legal": true
  },
  "DECREE_A55_P1": {
    "applicability": false,
    "legal": true
  },
  "DECREE_A55_P2": {
    "applicability": false,
    "legal": true
  },
  "DECREE_A56": {
    "applicability": false,
    "legal": true
  },
  "DECREE_A57": {
    "applicability": false,
    "legal": true
  },
  "DECREE_C8": {
    "applicability": false,
    "legal": true
  },
  "DECREE_A58": {
    "applicability": false,
    "legal": true
  },
  "DECREE_A58_P1": {
    "applicability": false,
    "legal": true
  },
  "DECREE_A58_P2": {
    "applicability": false,
    "legal": true
  },
  "DECREE_A59": {
    "applicability": false,
    "legal": true
  },
  "DECREE_A60": {
    "applicability": false,
    "legal": true
  },
  "DECREE_A60_P1": {
    "applicability": false,
    "legal": true
  },
  "DECREE_A60_P2": {
    "applicability": false,
    "legal": true
  },
  "DECREE_A60_P3": {
    "applicability": false,
    "legal": true
  },
  "DECREE_A60_P4": {
    "applicability": false,
    "legal": true
  },
  "DECREE_A60_P5": {
    "applicability": false,
    "legal": true
  },
  "DECREE_A60_P6": {
    "applicability": false,
    "legal": true
  },
  "DECREE_A60_P7": {
    "applicability": false,
    "legal": true
  },
  "DECREE_A60_2": {
    "applicability": false,
    "legal": true
  },
  "DECREE_A60_2_P1": {
    "applicability": false,
    "legal": true
  },
  "DECREE_A60_2_P2": {
    "applicability": false,
    "legal": true
  },
  "DECREE_A60_2_P2_S1": {
    "applicability": false,
    "legal": true
  },
  "DECREE_A60_2_P2_S1_Ia": {
    "applicability": false,
    "legal": true
  },
  "DECREE_A60_2_P2_S1_Ib": {
    "applicability": false,
    "legal": true
  },
  "DECREE_A60_2_P2_S1_Ic": {
    "applicability": false,
    "legal": true
  },
  "DECREE_A60_2_P2_S2": {
    "applicability": false,
    "legal": true
  },
  "DECREE_A60_2_P3": {
    "applicability": false,
    "legal": true
  },
  "DECREE_A60_2_P3_S1": {
    "applicability": false,
    "legal": true
  },
  "DECREE_A60_2_P3_S2": {
    "applicability": false,
    "legal": true
  },
  "DECREE_A60_2_P4": {
    "applicability": false,
    "legal": true
  },
  "DECREE_A60_2_P5": {
    "applicability": false,
    "legal": true
  },
  "DECREE_A60_2_P6": {
    "applicability": false,
    "legal": true
  },
  "DECREE_A60_3": {
    "applicability": false,
    "legal": true
  },
  "DECREE_A60_3_P1": {
    "applicability": false,
    "legal": true
  },
  "DECREE_A60_3_P2": {
    "applicability": false,
    "legal": true
  },
  "DECREE_A60_3_P3": {
    "applicability": false,
    "legal": true
  },
  "DECREE_A60_3_P4": {
    "applicability": false,
    "legal": true
  },
  "DECREE_A60_4": {
    "applicability": false,
    "legal": true
  },
  "DECREE_A60_4_P1": {
    "applicability": false,
    "legal": true
  },
  "DECREE_A60_4_P2": {
    "applicability": false,
    "legal": true
  },
  "DECREE_A60_4_P3": {
    "applicability": false,
    "legal": true
  },
  "DECREE_A60_5": {
    "applicability": false,
    "legal": true
  },
  "DECREE_A61": {
    "applicability": false,
    "legal": true
  },
  "DECREE_A61_P1": {
    "applicability": false,
    "legal": true
  },
  "DECREE_A61_P1_S1": {
    "applicability": false,
    "legal": true
  },
  "DECREE_A61_P1_S2": {
    "applicability": false,
    "legal": true
  },
  "DECREE_A61_P1_S3": {
    "applicability": false,
    "legal": true
  },
  "DECREE_A61_P2": {
    "applicability": false,
    "legal": true
  },
  "DECREE_A61_P2_S1": {
    "applicability": false,
    "legal": true
  },
  "DECREE_A61_P2_S2": {
    "applicability": false,
    "legal": true
  },
  "DECREE_A61_P2_S3": {
    "applicability": false,
    "legal": true
  },
  "DECREE_A61_P3": {
    "applicability": false,
    "legal": true
  },
  "DECREE_A61_P4": {
    "applicability": false,
    "legal": true
  },
  "DECREE_A62": {
    "applicability": false,
    "legal": true
  },
  "DECREE_A62_P1": {
    "applicability": false,
    "legal": true
  },
  "DECREE_A62_P2": {
    "applicability": false,
    "legal": true
  },
  "DECREE_A62_P2_S1": {
    "applicability": false,
    "legal": true
  },
  "DECREE_A62_P2_S2": {
    "applicability": false,
    "legal": true
  },
  "DECREE_A62_P2_S3": {
    "applicability": false,
    "legal": true
  },
  "DECREE_A62_P3": {
    "applicability": false,
    "legal": true
  },
  "DECREE_A62_P3_S1": {
    "applicability": false,
    "legal": true
  },
  "DECREE_A62_P3_S2": {
    "applicability": false,
    "legal": true
  },
  "DECREE_A62_P3_S3": {
    "applicability": false,
    "legal": true
  },
  "DECREE_A62_P3_S4": {
    "applicability": false,
    "legal": true
  },
  "DECREE_A62_P3_S5": {
    "applicability": false,
    "legal": true
  },
  "DECREE_A62_P3_S6": {
    "applicability": false,
    "legal": true
  },
  "DECREE_A62_P3_S7": {
    "applicability": false,
    "legal": true
  },
  "DECREE_A62_P3_S8": {
    "applicability": false,
    "legal": true
  },
  "DECREE_A62_P3_S8_Ia": {
    "applicability": false,
    "legal": true
  },
  "DECREE_A62_P3_S8_Ib": {
    "applicability": false,
    "legal": true
  },
  "DECREE_A62_P3_S9": {
    "applicability": false,
    "legal": true
  },
  "DECREE_A62_P3_S10": {
    "applicability": false,
    "legal": true
  },
  "DECREE_A62_P3_S10_Ia": {
    "applicability": false,
    "legal": true
  },
  "DECREE_A62_P3_S10_Ib": {
    "applicability": false,
    "legal": true
  },
  "DECREE_A62_P3_S10_Ic": {
    "applicability": false,
    "legal": true
  },
  "DECREE_A62_P3_S11": {
    "applicability": false,
    "legal": true
  },
  "DECREE_A62_P4": {
    "applicability": false,
    "legal": true
  },
  "DECREE_A62_P4_S1": {
    "applicability": false,
    "legal": true
  },
  "DECREE_A62_P4_S2": {
    "applicability": false,
    "legal": true
  },
  "DECREE_A62_P5": {
    "applicability": false,
    "legal": true
  },
  "DECREE_A62_2": {
    "applicability": false,
    "legal": true
  },
  "DECREE_A62_2_P1": {
    "applicability": false,
    "legal": true
  },
  "DECREE_A62_2_P1_S1": {
    "applicability": false,
    "legal": true
  },
  "DECREE_A62_2_P1_S2": {
    "applicability": false,
    "legal": true
  },
  "DECREE_A62_2_P1_S3": {
    "applicability": false,
    "legal": true
  },
  "DECREE_A62_2_P1_S4": {
    "applicability": false,
    "legal": true
  },
  "DECREE_A62_2_P1_S5": {
    "applicability": false,
    "legal": true
  },
  "DECREE_A62_2_P1_S6": {
    "applicability": false,
    "legal": true
  },
  "DECREE_A62_2_P1_S7": {
    "applicability": false,
    "legal": true
  },
  "DECREE_A62_2_P2": {
    "applicability": false,
    "legal": true
  },
  "DECREE_A62_2_P3": {
    "applicability": false,
    "legal": true
  },
  "DECREE_A62_3": {
    "applicability": false,
    "legal": true
  },
  "DECREE_A62_3_P1": {
    "applicability": false,
    "legal": true
  },
  "DECREE_A62_3_P1_S1": {
    "applicability": false,
    "legal": true
  },
  "DECREE_A62_3_P1_S2": {
    "applicability": false,
    "legal": true
  },
  "DECREE_A62_3_P1_S3": {
    "applicability": false,
    "legal": true
  },
  "DECREE_A62_3_P1_S4": {
    "applicability": false,
    "legal": true
  },
  "DECREE_A62_3_P1_S5": {
    "applicability": false,
    "legal": true
  },
  "DECREE_A62_3_P1_S6": {
    "applicability": false,
    "legal": true
  },
  "DECREE_A62_3_P1_S7": {
    "applicability": false,
    "legal": true
  },
  "DECREE_A62_3_P1_S8": {
    "applicability": false,
    "legal": true
  },
  "DECREE_A62_3_P1_S9": {
    "applicability": false,
    "legal": true
  },
  "DECREE_A62_3_P2": {
    "applicability": false,
    "legal": true
  },
  "DECREE_A62_3_P2_S1": {
    "applicability": false,
    "legal": true
  },
  "DECREE_A62_3_P2_S2": {
    "applicability": false,
    "legal": true
  },
  "DECREE_A62_3_P2_S3": {
    "applicability": false,
    "legal": true
  },
  "DECREE_A62_3_P3": {
    "applicability": false,
    "legal": true
  },
  "DECREE_A63": {
    "applicability": false,
    "legal": true
  },
  "transfers_overseas": false,
  "received_consent": false,
  "BUSINESS_DISPOSES_PERSONAL_DATA": false,
  "DETAILED_DISPOSAL_METHODS": false,
  "raise_exception": false,
  "handling_electronic_files": true,
  "PHYSICAL_DISPOSAL_METHODS_COMPLIANT": false,
  "BUSINESS_CONDUCTS_PROCESSING_WITH_CONSENT": false,
  "BUSINESS_ALLOW_FREE_CONSENT_DECISION": false,
  "BUSINESS_CONSENT_SPECIFIC_AND_CLEAR": false,
  "BUSINESS_CONSENT_TEXT_EASILY_UNDERSTANDABLE": false,
  "BUSINESS_PROVIDES_CLEAR_CONSENT_METHOD": false,
  "BUSINESS_USES_WRITTEN_CONSENT_METHOD": false,
  "BUSINESS_SOLICITS_CONSENT_VIA_PHONE": false,
  "BUSINESS_PHONE_NOTIFICATION_CLARITY": false,
  "BUSINESS_CONFIRM_EXPLICIT_PHONE_CONSENT": false,
  "BUSINESS_PROVIDES_ONLINE_CONSENT": false,
  "BUSINESS_ONLINE_CONSENT_IS_CLEAR": false,
  "BUSINESS_IS_PROCESSING_PERSONAL_INFORMATION": true,
  "BUSINESS_OBTAINS_CONSENT_VIA_EMAIL": false,
  "BUSINESS_USES_EQUIVALENT_CONSENT_METHOD": false,
  "BUSINESS_INFORMS_CONTACT_FOR_MARKETING": false,
  "BUSINESS_PROCESSES_SENSITIVE_INFO": false,
  "business_inform_storage_use_period": false,
  "BUSINESS_INFORMS_DATA_RECIPIENT_PURPOSE_OF_USE": false,
  "BUSINESS_INFORMS_CONSENT_METHOD": false,
  "BUSINESS_IS_SECTOR_GOVERNED": true,
  "BUSINESS_PROCESSES_UNIQUE_IDENTIFIERS": false,
  "BUSINESS_IS_PUBLIC_AGENCY": false,
  "BUSINESS_HAS_HISTORY_OF_VIOLATIONS": true,
  "DATA_SUBJECTS_OVER_50000": false,
  "DATA_SUBJECTS_OVER_10000": false,
  "BUSINESS_HAS_DATA_CERTIFICATION": false,
  "ONGOING_EVALUATION_UNDER_OTHER_LAWS": false,
  "REQUESTED_BY_HEAD_OF_RELEVANT_AGENCY": false,
  "RECOGNIZED_BY_COMMISION_AS_EQUIVALENT_TO_PHASE3_INSPECTION": false,
  "submitted_materials": false,
  "BUSINESS_PROCESSES_RESIDENT_REGISTRATION_NUMBERS_ELECTRONICALLY": false,
  "DATA_SUBJECTS_UNDER_1000000": false,
  "ENCRYPTION_COMPLIANCE_BEFORE_2017": false,
  "ENCRYPTION_COMPLIANCE_BEFORE_2018": false,
  "BUSINESS_TEMPORARILY_PROCESSES_VIDEO_FOR_STATISTICS": false,
  "similar_case_as_statistics_processing": false,
  "REVIEWED_AND_APPROVED_BY_PROTECTION_COMMISSION": false,
  "BUSINESS_IS_OPERATING_PRESCRIBED_FACILITIES": false,
  "CENTRAL_MINISTRIES_ENCOURAGE_GUIDELINES_COMPLIANCE": false,
  "BUSINESS_HAS_DATA_HANDLING_ENTITIES": true,
  "BUSINESS_LIMITS_PERSONAL_DATA_ACCESS_AND_SECURES": false,
  "BUSINESS_HAS_LIABILITY_ARRANGEMENTS_FOR_BREACHES": false,
  "BUSINESS_DISPLAYS_DELEGATION_ON_WEBSITE": false,
  "BUSINESS_POSTS_DELEGATION_INFO_PHYSICALLY": false,
  "BUSINESS_UTILIZES_OFFICIAL_PUBLICATIONS": false,
  "BUSINESS_USES_PERIODICALS_FOR_DISCLOSURE": false,
  "BUSINESS_INCLUDES_DELEGATION_IN_CONTRACTS": false,
  "uses_written_method": false,
  "INTERNET_WEBSITE_AVAILABLE": false,
  "BUSINESS_WISHES_TO_TRANSFER_PERSONAL_DATA": false,
  "can_notify_data_subjects_by_written_method": false,
  "can_use_website": false,
  "POSTED_DELEGATION_INFO_PHYSICALLY_FOR_30_DAYS": false,
  "inform_data_subjects_via_offline_media": false,
  "BUSINESS_PROCESSES_PSEUDONYMOUS_DATA": false,
  "BUSINESS_SEPARATELY_STORES_PSEUDONYMOUS_AND_ADDITIONAL_DATA": false,
  "ADDITIONAL_DATA_IS_UNNECESSARY": false,
  "ADDITIONAL_DATA_DESTROYED": false,
  "BUSINESS_IS_MICRO_ENTERPRISE": false,
  "pseudonym_processing_unable_due_to_resource_limitations": false,
  "provides_pseudonymized_data_to_third_party": false,
  "BUSINESS_RECORDS_PSEUDONYMOUS_DATA_RECIPIENT": false,
  "BUSINESS_HAS_DEFINED_PSEUDONYM_PROCESSING_PERIOD": false,
  "A29_10_P1_S1_compliant": false,
  "A29_10_P1_S2_compliant": false,
  "A29_10_P1_S3_compliant": false,
  "CONTRACT_INCLUDES_FOREIGN_TRANSFER_PROTECTION_MEASURES": false,
  "INTERNAL_MANAGEMENT_PLAN_ESTABLISHED": false,
  "INTERNAL_MANAGEMENT_PLAN_IMPLEMENTED": false,
  "INTERNAL_MANAGEMENT_PLAN_MONITORED": false,
  "BUSINESS_IS_OPERATING_DATABASE_SYSTEM": false,
  "BUSINESS_HAS_ACCESS_CONTROL_STANDARDS": false,
  "BUSINESS_APPLIES_AUTHENTICATION_MEASURES": false,
  "DECREE_A30_P1_S3_Ia_compliant": false,
  "DECREE_A30_P1_S3_Ib_compliant": false,
  "DECREE_A30_P1_S3_Ic_compliant": false,
  "avg_daily_users_over_1000000": false,
  "INTERNET_ACCESS_RESTRICTED": false,
  "BUSINESS_SECURES_STORAGE_AND_TRANSMISSION": false,
  "Encryption_Of_Resident_Registration_Numbers": false,
  "DATA_TRANSMISSION_ENCRYPTED": false,
  "DECREE_A30_P1_S5_Ia_compliant": false,
  "DECREE_A30_P1_S5_Ib_compliant": false,
  "DECREE_A30_P1_S5_Ic_compliant": false,
  "BUSINESS_TAKES_PRECAUTIONS_TO_PREVENT_RECORD_TAMPERING": false,
  "DECREE_A30_P1_S6_compliant": false,
  "PHYSICAL_SECURITY_MEASURES_IN_PLACE": false,
  "can_be_supported_by_protection_commission": true,
  "BUSINESS_COLLECTS_AND_PROCESSES_PERSONAL_DATA_EXTERNALLY": false,
  "BUSINESS_POSTS_PRIVACY_POLICY_ON_WEBSITE": false,
  "BUSINESS_INCLUDES_POLICY_IN_CONTRACTS": false,
  "BUSINESS_TOTAL_REVENUE_OVER_1_TRILLION_WON": false,
  "DECREE_A32_3_P1_S3_compliant": false,
  "data_breach_occurred": true,
  "PERSONAL_DATA_LOST_OR_STOLEN": true,
  "PERSONAL_DATA_LEAKED": true,
  "notify_data_subjects_within_72_hours": true,
  "EMERGENCY_MEASURES_REQUIRED": false,
  "can_delay_notification_due_to_emergency": false,
  "LAW_A34_P1_S1_SPECIFIED": false,
  "LAW_A34_P1_S2_SPECIFIED": false,
  "notify_data_subjects_with_available_info": true,
  "PART_OF_DECREE_A40_APPLICABILITY": true,
  "emergency_situation": false,
  "DATA_SUBJECTS_OVER_1000": false,
  "notify_commission_and_specialized_agency_within_72_hours": false,
  "business_is_data_controller": true,
  "DATA_SUBJECT_REQUESTS_ACCESS": false,
  "DIFFICULTY_IN_CONTINUING_DATA_COLLECTION_OUTLET": false,
  "DATA_ACCESS_REQUEST_HANDLED_IN_SAME_WAY_AS_COLLECTION": false,
  "BUSINESS_POSTS_DATA_ACCESS_PROCEDURE_ON_WEBSITE": false,
  "notify_data_subjects_within_10_days": false,
  "IMMEDIATE_ACCESS_GRANTED": false,
  "DECREE_ROOT": {
    "applicability": true,
    "legal": false
  },
  "SET_PROTECTION_COMMITTEE_GUIDELINES": true,
  "RECOMMEND_APPROPRIATE_CONSENT_METHODS": true,
  "Commission_may_set_detailed_encryption_guidelines": true,
  "notify_data_subjects_before_complete_details": true
}